[
  {
    "id": "1n3ng4k",
    "source": "reddit",
    "subreddit": "r/ragincajuns",
    "title": "Made this one just in time for the season opener, and wanted to share here.",
    "body": "CNC designed and carved.  I thought it came out great.  ",
    "url": "https://www.reddit.com/gallery/1n3ng4k",
    "upvotes": 39,
    "date": "2025-08-30T00:07:50.000Z",
    "author": "meauxda",
    "top_comments": [
      {
        "text": "Geaux Cajuns ⚜️",
        "upvotes": 3,
        "author": "[deleted]",
        "date": "2025-08-30T08:46:28.000Z"
      },
      {
        "text": "Awesome, you sell those?",
        "upvotes": 2,
        "author": "RaginRealtor",
        "date": "2025-08-30T12:39:28.000Z"
      },
      {
        "text": "It really pops!  Great job 👏",
        "upvotes": 2,
        "author": "ihatetothat1",
        "date": "2025-08-30T12:43:38.000Z"
      },
      {
        "text": "That’s beautiful",
        "upvotes": 2,
        "author": "Mytmouse069",
        "date": "2025-09-04T18:58:50.000Z"
      },
      {
        "text": "Be careful. ULL is getting really touchy about brand licensing.",
        "upvotes": 1,
        "author": "wotipka",
        "date": "2025-08-31T02:52:57.000Z"
      },
      {
        "text": "How much/where do we buy",
        "upvotes": 1,
        "author": "Aggressive_Hawk_8338",
        "date": "2025-09-04T19:05:23.000Z"
      }
    ]
  },
  {
    "id": "1swfu8s",
    "source": "reddit",
    "subreddit": "r/ragincajuns",
    "title": "Cajun Drafted!",
    "body": "Congratulations to former Cajun Jaden Dugger on being drafted by the San Francisco 49ers this weekend!",
    "url": "https://i.redd.it/qlzk3rqbykxg1.jpeg",
    "upvotes": 16,
    "date": "2026-04-26T18:43:39.000Z",
    "author": "SunBeltSyndicate",
    "top_comments": [
      {
        "text": ". #GeauxCajuns #WeAreLouisiana",
        "upvotes": 2,
        "author": "CajunDreDog",
        "date": "2026-04-26T19:42:04.000Z"
      }
    ]
  },
  {
    "id": "1nsqdzv",
    "source": "reddit",
    "subreddit": "r/ragincajuns",
    "title": "Cajuns Shock in Comeback",
    "body": "A rematch of the 2024 Sun Belt Championship was everything we wanted the December matchup to be. Louisiana outlasted Marshall in 2OT!\n\nWelcome Tory Trahan to the Syndicate with his first article!",
    "url": "https://sunbeltsyndicate.com/louisiana-wins-in-a-thriller-against-marshall-in-double-ot-2025/",
    "upvotes": 15,
    "date": "2025-09-28T14:55:32.000Z",
    "author": "SunBeltSyndicate",
    "top_comments": [
      {
        "text": "What a game!!! Wish I wouldn't have left early. Ugh. Regret is setting in today as to what I missed.\n\n#GeauxCajuns #WeAreLouisiana #RaginCajuns #CajunNation #cULture #FunBelt",
        "upvotes": 2,
        "author": "CajunDreDog",
        "date": "2025-09-29T03:52:34.000Z"
      }
    ]
  },
  {
    "id": "1n00e4y",
    "source": "reddit",
    "subreddit": "r/ragincajuns",
    "title": "University of Louisiana at Lafayette IDs now double as public library cards",
    "body": "",
    "url": "https://www.msn.com/en-us/news/us/university-of-louisiana-at-lafayette-ids-now-double-as-public-library-cards/ar-AA1L9M0o?ocid=BingNewsVerp",
    "upvotes": 13,
    "date": "2025-08-25T19:39:11.000Z",
    "author": "crabcakes110",
    "top_comments": []
  },
  {
    "id": "1n47oer",
    "source": "reddit",
    "subreddit": "r/ragincajuns",
    "title": "New stadium, quarterback to be unveiled against Rice",
    "body": "",
    "url": "https://www.theadvocate.com/acadiana/sports/ul_lafayette/our-lady-of-lourdes-stadium-walker-howard-cajuns/article_c6eaa853-e979-47e5-ab2b-57957d77596b.html",
    "upvotes": 12,
    "date": "2025-08-30T17:40:00.000Z",
    "author": "mikebass",
    "top_comments": []
  },
  {
    "id": "1oraqaf",
    "source": "reddit",
    "subreddit": "r/ragincajuns",
    "title": "Fan Made Mascot Makes Tailgate Debut",
    "body": "",
    "url": "https://i.redd.it/8x458k19dxzf1.png",
    "upvotes": 11,
    "date": "2025-11-08T00:08:30.000Z",
    "author": "cms9607",
    "top_comments": []
  },
  {
    "id": "1n9ya1u",
    "source": "reddit",
    "subreddit": "r/ragincajuns",
    "title": "New Sub Rules",
    "body": "Hi all! We've updated the SubReddit rules to be more expansive. These are in-line with /Acadiana and other local, popular subs. Nothing crazy! The updated rules are:\n\n• Keep discussions civil.\n\n• No advertising.\n\n• No Racism, Bigotry, or Misogyny\n\n(No Bigotry or Hate Speech with regard to gender, race, ethnicity, disability, sexual orientation, sexual identity, national origin, or any other distinguishing characteristic or trait.)\n\n• No sensationalized post titles\n\n(Link posts headlines should be the original article's headline only. Sensationalized or editorialized post titles written by the posting user are not allowed.)\n\n• Posts should be about UL's Ragin' Cajuns\n\n(Posts made in this subreddit should be about the University of Louisiana at Lafayette, Ragin' Cajun athletics, or a topic tangentially related to student-living. If a post is deemed too random or unrelated it may be deleted.)",
    "url": "https://www.reddit.com/r/ragincajuns/comments/1n9ya1u/new_sub_rules/",
    "upvotes": 10,
    "date": "2025-09-06T12:27:09.000Z",
    "author": "BoudinAmbassador",
    "top_comments": []
  },
  {
    "id": "1qkdmz1",
    "source": "reddit",
    "subreddit": "r/ragincajuns",
    "title": "Should I come to ULL?",
    "body": "I'm in state about 2 hours away from UL and I've only been to the campus once for a band competition. I honestly don't know much about UL since I don't know anyone who's gone there/is there personally. I've heard plenty of things about it but I'm just not sure if I should go. I really love the campus though and if I would end up going I'd be an education major. ",
    "url": "https://www.reddit.com/r/ragincajuns/comments/1qkdmz1/should_i_come_to_ull/",
    "upvotes": 9,
    "date": "2026-01-23T01:51:02.000Z",
    "author": "Zestyclose_Elk8688",
    "top_comments": [
      {
        "text": "Ive attended 2 colleges, 1 being UL and worked at 3 other colleges. I think its honestly about the same experience you get at most other similarly priced colleges. It has some great programs and some that are just meh. Dorms are nicer if you can pay more but its still dorm living at end of the day. Even expensive SEC schools are comparable there.",
        "upvotes": 7,
        "author": "Strylan",
        "date": "2026-01-23T03:15:35.000Z"
      },
      {
        "text": "My kid is there right now and she is enjoying it. Granted, she got a single dorm and is quite the homebody, so her experience might be different than others.",
        "upvotes": 4,
        "author": "dog-fart",
        "date": "2026-01-23T03:37:47.000Z"
      },
      {
        "text": "Yes, I am a former band kid going to UL and also am going to be an education major 😌😌😌What subject are you concentrating on",
        "upvotes": 1,
        "author": "Friendly_Bonus_3220",
        "date": "2026-01-24T04:55:56.000Z"
      },
      {
        "text": "No, UL is terrible! I went there for 3 yrs then transferred, even though it added on a year to my education. Best decision ever! My only regret was not doing it sooner.\n\nI have had multiple professors literally say that their job isn't to teach. I understand that at UL, they are mostly concerned with research, but students are paying them to teach. There were a couple however, that were happy to meet outside of class during office hours to discuss their classes.\n\nNot to mention, the facilities are absolutely terrible, and so was the administration. Although, the administration has since changed.\n\nBest of luck in your college journey!",
        "upvotes": 1,
        "author": "No_Fill_6005",
        "date": "2026-01-24T13:16:13.000Z"
      },
      {
        "text": "They can barely afford to keep the lights on. Don’t set the bar so low as you enter adulthood.",
        "upvotes": 0,
        "author": "Melodic-Pangolin-434",
        "date": "2026-01-23T06:36:39.000Z"
      },
      {
        "text": "Honestly from a current student? No. I came here from 4 hours away, and if it weren’t for the friends I made (can do that at any college) I’d regret coming here. The tours only really show the good parts of campus, they don’t have enough space every semester they bite off more than they can chew attendance wise, so much of campus is under construction it doesn’t even look nice lately, and somehow we’re millions in debt. I know every college has its horror stories but I genuinely don’t recommend here as ur first or hell even second choice for college.",
        "upvotes": -3,
        "author": "D3mon1c1mp",
        "date": "2026-01-23T02:30:09.000Z"
      }
    ]
  },
  {
    "id": "1n52rw2",
    "source": "reddit",
    "subreddit": "r/ragincajuns",
    "title": "Rice Game Recap",
    "body": "High expectations, a newly renovated stadium, but a loss to open at home for the Cajuns. What happened against Rice?\n\nOur Cade Williams has more. ",
    "url": "https://sunbeltsyndicate.com/louisiana-drop-nail-biter-to-rice-in-opener/",
    "upvotes": 9,
    "date": "2025-08-31T18:52:53.000Z",
    "author": "SunBeltSyndicate",
    "top_comments": [
      {
        "text": "Needs a proof reader.",
        "upvotes": 1,
        "author": "TimmySouthSideyeah",
        "date": "2025-08-31T21:02:20.000Z"
      }
    ]
  },
  {
    "id": "1qokewi",
    "source": "reddit",
    "subreddit": "r/ragincajuns",
    "title": "Double majoring",
    "body": "As a freshman in EECE, I noticed there aren’t too many more credits to major in Math. Is there a way to take the extra credits needed online and just pay out of pocket either through UL, SLCC, or any online college? Will UL allow me to double major?",
    "url": "https://www.reddit.com/r/ragincajuns/comments/1qokewi/double_majoring/",
    "upvotes": 8,
    "date": "2026-01-27T17:30:32.000Z",
    "author": "StraightPut6353",
    "top_comments": [
      {
        "text": "you can take credits at SLCC they’ll transfer easily but double majoring at UL seems easier. \nIt’ll only add an extra year to your education. They have resources for accelerated double majors \nlook on the website",
        "upvotes": 1,
        "author": "cuntry1738",
        "date": "2026-01-31T04:35:54.000Z"
      }
    ]
  },
  {
    "id": "1nf7w6c",
    "source": "reddit",
    "subreddit": "r/ragincajuns",
    "title": "Questions on starting a club?",
    "body": "I'm currently in my second semester at ul and none of the current clubs have really interested me. I'm in the aquarium/fish keeping hobby and was hoping I could find some type of organization that aligned with my interests. So far non so I have been researching the guidelines and requirements on starting a club and I'm certain that I can try starting one if I put in some effort. I'd like to start an aquarium club that has a focus on bringing people in the same hobby together to share information and experience. For the two main questions I have\n\n1. How should I go about finding people who are interested in the club I want to start? The club I want to start is kind of niche and I don't know many people at ul. \n\n2. I know an advisor for the club is needed, how should I go about finding an advisor and asking?\n\nThe aquarium hobby is a genuine joy for me. I'd like to be able to build a community of people I can talk to and share with. (It's frustrating when I have something I'm excited about and no one to share with)\n\n\n\n",
    "url": "https://www.reddit.com/r/ragincajuns/comments/1nf7w6c/questions_on_starting_a_club/",
    "upvotes": 7,
    "date": "2025-09-12T16:31:40.000Z",
    "author": "Neither_Lifeguard_26",
    "top_comments": [
      {
        "text": "[https://getinvolved.louisiana.edu/student-organizations/start-new-organization](https://getinvolved.louisiana.edu/student-organizations/start-new-organization)",
        "upvotes": 1,
        "author": "grumpyolddude",
        "date": "2025-09-12T16:37:01.000Z"
      }
    ]
  },
  {
    "id": "1pr23z2",
    "source": "reddit",
    "subreddit": "r/ragincajuns",
    "title": "OOS ULL vs. ULM",
    "body": "I'm from California, however have a good chunk of my family in Louisiana. I've been offered full ride to UL Monroe, and around \\~20K to attend UL Lafayette. I like free, however I've heard Monroe is a little on the dead side compared to Lafayette, with it being more rural and everything. Is ULL worth the price tag?",
    "url": "https://www.reddit.com/r/ragincajuns/comments/1pr23z2/oos_ull_vs_ulm/",
    "upvotes": 6,
    "date": "2025-12-20T01:34:21.000Z",
    "author": "No-Fill-993",
    "top_comments": [
      {
        "text": "You'll enjoy Lafayette more than Monroe.",
        "upvotes": 14,
        "author": "motherfuckinwoofie",
        "date": "2025-12-20T01:59:31.000Z"
      },
      {
        "text": "Not saying anything poor about Monroe… the Lafayette Area (Acadiana) and New Orleans are the epicenters of culture in Louisiana. I think even people from Monroe would agree. I am from Acadiana but have spent time all over the state. From culture to nightlife, food, music, Mardi Gras, and more, there is no comparison. Lafayette is even much closer to Baton Rouge, and NOLA if you decide to go explore. If you are looking to have a relatively quiet college experience, Monroe is probably for you. It is definitely more rural and you probably won’t have to drive as far if you choose to go deer or duck hunting. ULM does have some very good degree programs that UL Lafayette does not have such as Pharmacy and Construction Management - in fact, ULM’s construction program is top rated in the country. Lafayette just has so much more going on. Good luck.",
        "upvotes": 6,
        "author": "Knicco",
        "date": "2025-12-20T02:10:12.000Z"
      },
      {
        "text": "Culturally, Lafayette will be the better fit.",
        "upvotes": 3,
        "author": "No_Abroad_6306",
        "date": "2025-12-20T06:27:24.000Z"
      },
      {
        "text": "I have tons of people from Monroe in all my classes if that says anything",
        "upvotes": 2,
        "author": "ghostfire457",
        "date": "2025-12-20T22:51:34.000Z"
      },
      {
        "text": "So full ride to ULM and 20k in scholarships to UL total? I’m biased so I’ll say come on down the bottom and go to Louisiana. engineering program is top-notch.",
        "upvotes": 2,
        "author": "lockz_up",
        "date": "2025-12-21T16:35:15.000Z"
      },
      {
        "text": "I’m from Lafayette, and made the decision to go to ULM. There are a number of things that influenced my decision, money being one of them. UL doesn’t have my major, which was a solid enough reason on its own.\n\nCulturally, Lafayette is superior by a landslide. There are times when it feels like there’s nothing to do in laffy but man it’s true 100x more in Monroe. \n\nCost of living in Lafayette is higher than in Monroe.  ULM is cheaper than UL, though there is less to do in Monroe. \n\nOverall, Monroe isn’t completely dead. West Monroe is less than 15 minutes away, Ruston 45 minutes. Lafayette traffic is way worse. The food up north just doesn’t compare to what’s available down south. Personally, I think ULM was right for me, but it depends on what field you’re going into and what your means are.",
        "upvotes": 2,
        "author": "CartographerFar8663",
        "date": "2025-12-22T23:27:44.000Z"
      },
      {
        "text": "Being from California, I think Monroe would be too slow and boring for you. There is no party scene or anything fun to do.  Everything closes early on campus because it’s a commuter school. Lafayette has more nightlife and their school is 3x bigger than Monroe.",
        "upvotes": 1,
        "author": "johall446",
        "date": "2025-12-21T23:55:07.000Z"
      }
    ]
  },
  {
    "id": "1os5swg",
    "source": "reddit",
    "subreddit": "r/ragincajuns",
    "title": "Play caller",
    "body": "I don’t know who the guy is doing the job and is doing a great job “except” for his “guessing what the penalty calls are”. He is wrong more than 50% of the time maybe. Just wait for the official call. JMA. ",
    "url": "https://www.reddit.com/r/ragincajuns/comments/1os5swg/play_caller/",
    "upvotes": 5,
    "date": "2025-11-09T00:58:47.000Z",
    "author": "Chu-Plat",
    "top_comments": [
      {
        "text": "What?",
        "upvotes": 1,
        "author": "CajunDreDog",
        "date": "2025-11-09T05:36:46.000Z"
      },
      {
        "text": "If you're talking about the radio guys, you're probably talking about Jay Walker. He does the play by play, and Cody Juneau does the analysis. Jay is pretty great (so is Cody). He's been doing this for decades. He might be wrong on penalties because the Sun Belt refs (like all officials) are wrong most of the time... especially when they throw the flag on the Cajuns. I've noticed that he is usually off by 1 yd from where the official spot of the ball is by the officials. It's probably hard to see the field from way up in the box.",
        "upvotes": 1,
        "author": "MangeurDeCowan",
        "date": "2025-11-10T00:56:34.000Z"
      }
    ]
  },
  {
    "id": "1lti6c5",
    "source": "reddit",
    "subreddit": "r/ragincajuns",
    "title": "Calling All Powerlifters!",
    "body": "Are you a powerlifter? Come check out r/LouisianaPowerlifting !\n\nCurrently trying to grow the community — as of now there’s only two members but I know there’s plenty more scattered throughout Reddit.\n\nI’m currently working to overhaul the look and feel of the sub and would love some input to make it a great place of information for Louisiana-based lifter",
    "url": "https://www.reddit.com/r/ragincajuns/comments/1lti6c5/calling_all_powerlifters/",
    "upvotes": 5,
    "date": "2025-07-07T01:54:39.000Z",
    "author": "barmen1",
    "top_comments": []
  },
  {
    "id": "1smfxka",
    "source": "reddit",
    "subreddit": "r/ragincajuns",
    "title": "For current UL students: I am doing a short survey for Louisiana college students about their feelings on Louisiana French/Louisiana Creole. Any response would be appreciated, thank you!",
    "body": "[https://docs.google.com/forms/d/e/1FAIpQLSdT6DOSp-6syq\\_Z-uRORodMstus4FW72IO18SiuGTMQbRmF9A/viewform?usp=sharing&amp;ouid=109609081225102645907](https://docs.google.com/forms/d/e/1FAIpQLSdT6DOSp-6syq_Z-uRORodMstus4FW72IO18SiuGTMQbRmF9A/viewform?usp=sharing&amp;ouid=109609081225102645907)",
    "url": "https://www.reddit.com/r/ragincajuns/comments/1smfxka/for_current_ul_students_i_am_doing_a_short_survey/",
    "upvotes": 5,
    "date": "2026-04-15T19:17:19.000Z",
    "author": "Swim_Medical",
    "top_comments": [
      {
        "text": "I feel like the \"do you have cajun heritage\" question should be expanded to include broadly creole heritage, if the goal is to see how many people have louisiana-french heritage",
        "upvotes": 1,
        "author": "charlalalan",
        "date": "2026-04-15T19:34:23.000Z"
      }
    ]
  },
  {
    "id": "1nr28fg",
    "source": "reddit",
    "subreddit": "r/ragincajuns",
    "title": "2024 Title Game Rematch",
    "body": "The time has come for the Sun Belt Conference Championship rematch. But this time around both Marshall and Louisiana both look vastly different. \n\nCade Williams previews the 2025 version of this tilt. ",
    "url": "https://sunbeltsyndicate.com/week-five-preview-marshall-at-louisiana/",
    "upvotes": 4,
    "date": "2025-09-26T14:04:40.000Z",
    "author": "SunBeltSyndicate",
    "top_comments": []
  },
  {
    "id": "1naiq3y",
    "source": "reddit",
    "subreddit": "r/ragincajuns",
    "title": "Aussies trying to get to game",
    "body": "G'day all,\n\nMy wife and I are heading to Louisiana in November and want to come see a college football game. Specifically the 29th of November Cajuns vs LSU game.\n\nFor the life of me I can't seem to book tickets through the ragincajun website, or even the third party websites. It let's me choose the seats and everything but won't take any Visa or MasterCard cards I have.\n\nIs there a trick I'm missing? Maybe a secret locals only way to book?\n\nCheers for your help!\n",
    "url": "https://www.reddit.com/r/ragincajuns/comments/1naiq3y/aussies_trying_to_get_to_game/",
    "upvotes": 4,
    "date": "2025-09-07T03:21:36.000Z",
    "author": "Jammydry",
    "top_comments": [
      {
        "text": "It may not let you buy them online without a U.S. credit card. You can try contacting the ticket office directly at tickets@louisiana.edu or (337) 482-GoUL (4685). And see what they say\n\nAlso, just fyi, it looks like the November 29th game is again UL-Monroe, not LSU. Just be prepared for a different quality opponent (and that’s coming from a ULM alum 😅)",
        "upvotes": 11,
        "author": "fleur-de-tea",
        "date": "2025-09-07T04:33:36.000Z"
      },
      {
        "text": "LSU plays Oklahoma that day. LSU does not play ULL at all. That could be why you cannot purchase tickets. It’s not a real game.",
        "upvotes": 4,
        "author": "PandaGlobal4120",
        "date": "2025-09-07T23:56:21.000Z"
      },
      {
        "text": "ULL plays ULM.. University of Louisiana at Monroe that day. Sorry sir. Still go though, great scene and fun to watch.",
        "upvotes": 2,
        "author": "Cajunbot",
        "date": "2025-09-08T00:10:00.000Z"
      }
    ]
  },
  {
    "id": "1mjtkww",
    "source": "reddit",
    "subreddit": "r/ragincajuns",
    "title": "Tuition Statement Questions",
    "body": "Hi! Due to my Pellgrant, Fafsa, and scholarships being higher than my actual tuition, I have about 1k leftover. This is the first time that this happened to me too and I’m planning on using this money to buy textbooks and pay for my parking pass. Does anyone know what to do in this situation? Is there anyway for me to transfer my leftover money to my bank account so I can pay for the things previously mentioned? ",
    "url": "https://www.reddit.com/r/ragincajuns/comments/1mjtkww/tuition_statement_questions/",
    "upvotes": 4,
    "date": "2025-08-07T07:27:09.000Z",
    "author": "PurfectChicken",
    "top_comments": []
  },
  {
    "id": "1ncki5p",
    "source": "reddit",
    "subreddit": "r/ragincajuns",
    "title": "Paid Ambassador Opportunity",
    "body": "We’re looking for paid campus ambassadors to help spread the word about Professor Index at ULL. If you’re interested, please comment below or send me a direct message.\n\nThis role is perfect for a ULL student who’s looking for a unique tech/marketing project with real impact, and it’s a great opportunity for meaningful resume growth.\n\n",
    "url": "https://www.reddit.com/r/ragincajuns/comments/1ncki5p/paid_ambassador_opportunity/",
    "upvotes": 3,
    "date": "2025-09-09T14:30:54.000Z",
    "author": "NashMahmoud",
    "top_comments": [
      {
        "text": "Hey, is this role available for a Graduate student?",
        "upvotes": 0,
        "author": "[deleted]",
        "date": "2025-09-10T01:46:37.000Z"
      }
    ]
  },
  {
    "id": "1m2d1fs",
    "source": "reddit",
    "subreddit": "r/ragincajuns",
    "title": "Louisiana Ragin' Cajuns 2025 Football Team Preview",
    "body": "We recently sat down with Dawson Eiserloh, Host of the Loh Down on ESPN - SW Louisiana and Sideline Reporter for Ragin' Cajun Football to preview the 2025 Louisiana Ragin' Cajuns Football Team. Here is a link to the video if you are interested in hearing more! [2025 Louisiana Ragin' Cajuns Football Team Preview](https://youtu.be/zpjN3OgM_DY)\n\nIf you are looking for MORE G5 College Football Content Check Out our [YouTube Page](https://www.youtube.com/@G5Hive) and follow us on [X/Twitter](https://x.com/G5Hive)! Episodes are also available on  [Amazon Music](https://music.amazon.in/podcasts/da3cad9b-26b8-4a9e-b83a-ad8c9bd08df1/the-g5-hive), [Apple Podcasts](https://podcasts.apple.com/gb/podcast/the-g5-hive/id1704591509) and [Spotify](https://open.spotify.com/show/4Sd5XzJCLYiAcf18OGIzc3) if you rather listen in audio form.",
    "url": "https://www.reddit.com/r/ragincajuns/comments/1m2d1fs/louisiana_ragin_cajuns_2025_football_team_preview/",
    "upvotes": 3,
    "date": "2025-07-17T17:02:58.000Z",
    "author": "TheG5Hive",
    "top_comments": [
      {
        "text": "Great stuff! Thanks for posting it here",
        "upvotes": 1,
        "author": "[deleted]",
        "date": "2025-07-17T18:35:37.000Z"
      }
    ]
  },
  {
    "id": "1roa59w",
    "source": "reddit",
    "subreddit": "r/ragincajuns",
    "title": "Louisiana fans: which schools feel like the best long-term conference fits?",
    "body": "I am building a college football conference realignment map and I want fan input before I lock in one part of it.\n\nI made a list of schools that might fit with Louisiana. This list is only a starting point. I used my own limited knowledge and some guesswork to build it, so I do not expect it to be fully accurate. I want to hear from actual fans before I rely on it.\n\nI am also comparing a few different clustering approaches and building a new one from scratch, so this kind of fan feedback would directly help my understanding and any algorithm weights I may end up using.\n\nI am more interested in long-term fit based on rivalry history, fan culture, school identity, athletics, academics, and overall feel. Don't worry if the school you think is a good fit has no historic ties. If it feels like a school your fanbase admires and you could see them being a long-term fit, please include them.\n\n**How you can help**\n1. **The best help:** give your own weights and ignore mine\n2. Remove a team that does not belong\n3. Add a team I missed (please include the weight you would add them at)\n4. Move a team up or down (please include how far up or down you would move them)\n\n**Weight scale**\n- **5** = must-have conference fit\n- **4** = high-priority fit\n- **3** = strong fit\n- **2** = reasonable but not necessary fit\n- **1** = acceptable last resort fit if hard choices had to be made\n\n**My current list for Louisiana**\n\n**Weight 5**\n- UL Monroe, Southern Miss\n\n**Weight 4**\n- South Alabama, Troy\n- Arkansas State, Texas State\n- Tulane, Louisiana Tech\n\n**Weight 3**\n- South Florida, Memphis\n- UAB, UTSA\n\n**Weight 2**\n- Rice, North Texas\n- Tulsa, East Carolina\n- Marshall, App State\n- Coastal Carolina, Georgia Southern\n- Jacksonville State, Western Kentucky\n\n**Weight 1**\n- Georgia State, Middle Tennessee\n- FAU\n\n---\n\nSmall note: I am mainly looking for your fan perspective on which schools you would want around your program, not whether the final setup is practical or likely to happen in real life. If possible, go with your gut on fit more than logistics.\n\n*IMPORTANT:* This is not a list of a new conference. The amount of schools weighted should be much higher than the actual end result conference. The core of your ideal conference should be weight 5. Weights 4 and 3 should be the remainder of your dream conference. Weight 2 should be good options if flexibility is required. Weight 1 is last resort better than nothing.\n\n*The amount of weighted schools has no impact on the final conference size.*\n\nThis is really about full athletic conference fit, but I limited the school pool to FBS programs.\n\nI really appreciate any feedback on this, thanks so much for any help.",
    "url": "https://www.reddit.com/r/ragincajuns/comments/1roa59w/louisiana_fans_which_schools_feel_like_the_best/",
    "upvotes": 3,
    "date": "2026-03-08T17:06:13.000Z",
    "author": "Happy_Background_879",
    "top_comments": []
  },
  {
    "id": "1qf225j",
    "source": "reddit",
    "subreddit": "r/ragincajuns",
    "title": "Campus Cupboard",
    "body": "How does one go about using the campus cupboard? Really struggling this semester with bills/food. Do I just bring my UL ID and pick what I want? Or do they provide something already put together? Do I need to bring bags? The whole thing is anxiety inducing in itself. ",
    "url": "https://www.reddit.com/r/ragincajuns/comments/1qf225j/campus_cupboard/",
    "upvotes": 3,
    "date": "2026-01-17T03:23:01.000Z",
    "author": "Low-Bowl8584",
    "top_comments": [
      {
        "text": "Last time I used it, you bring your ID and tell them how large your household is, and then you get to pick certain items.",
        "upvotes": 4,
        "author": "drpalmerphd",
        "date": "2026-01-17T03:36:07.000Z"
      }
    ]
  },
  {
    "id": "1oo7ava",
    "source": "reddit",
    "subreddit": "r/ragincajuns",
    "title": "Laptop recommendations",
    "body": "My daughter will be starting Fall 2026 majoring in Kinesiology. I want to buy her a computer for Christmas, but some parents said to check what is compatible with her major. Would a MacBook Air be ok for this major?",
    "url": "https://www.reddit.com/r/ragincajuns/comments/1oo7ava/laptop_recommendations/",
    "upvotes": 3,
    "date": "2025-11-04T13:36:32.000Z",
    "author": "caramelcutie85",
    "top_comments": [
      {
        "text": "A MacBook air would likely be perfect. Since kinesiology is the study of body movement she will likely need to study documents and use a word processor for her major which any computer will do. Macbook air would be a great choice for portability around campus and will easily last her entire college career. Geaux Cajuns!",
        "upvotes": 5,
        "author": "TochsTouch",
        "date": "2025-11-04T14:23:17.000Z"
      },
      {
        "text": "Lenovo ThinkPad 1X",
        "upvotes": 1,
        "author": "[deleted]",
        "date": "2026-01-03T23:38:28.000Z"
      },
      {
        "text": "For the price of a Mac, look into the Framework line of laptops. Easy to upgrade parts such as the battery, memory, new keyboard for when something gets spilled. Also, runs windows 11 just fine. It will definitely get her through 4 years and maybe more. Also, no apple care needed for when the battery craps out after 6 months.",
        "upvotes": 0,
        "author": "wotipka",
        "date": "2025-11-04T18:47:15.000Z"
      }
    ]
  },
  {
    "id": "1ojcbtm",
    "source": "reddit",
    "subreddit": "r/ragincajuns",
    "title": "TOPS?",
    "body": "Has anyone already recieved tops, im tryign to figure out if theres a problem with my account or something, i know they ususally disburse it towards the end of october, but i still havent recieved anything yet, is anyone else having this problem?",
    "url": "https://www.reddit.com/r/ragincajuns/comments/1ojcbtm/tops/",
    "upvotes": 3,
    "date": "2025-10-29T18:23:06.000Z",
    "author": "Subject_Impress_3789",
    "top_comments": [
      {
        "text": "Is your account balance showing as 0? Once it goes down to 0 you can expect to get your refund shortly.",
        "upvotes": 1,
        "author": "Healthy_Combination3",
        "date": "2025-10-29T18:55:34.000Z"
      },
      {
        "text": "I got my tops at the beginning of October, were you supposed to receive a refund ?",
        "upvotes": 1,
        "author": "ghostfire457",
        "date": "2025-11-01T20:27:16.000Z"
      }
    ]
  },
  {
    "id": "1oh1xkv",
    "source": "reddit",
    "subreddit": "r/ragincajuns",
    "title": "Has anyone bought polymer clay from the campus store?",
    "body": "Someone bought this clay from the campus store a few years ago, and I have no idea what brand it is. I would really appreciate if someone knows what brand the campus store sells/has sold so I can get more!",
    "url": "https://i.redd.it/gxy589mx4kxf1.jpeg",
    "upvotes": 3,
    "date": "2025-10-27T01:34:23.000Z",
    "author": "Active-Mulberry-8275",
    "top_comments": []
  },
  {
    "id": "1ogsnvg",
    "source": "reddit",
    "subreddit": "r/ragincajuns",
    "title": "Cajuns Fall to Trojans",
    "body": "The Trojans march on while Cajuns cool, as Troy defeats Louisiana to earn bowl eligibility. \n\nSullivan Towe has more. ",
    "url": "https://sunbeltsyndicate.com/troy-defeats-louisiana-earning-bowl-eligibility/",
    "upvotes": 3,
    "date": "2025-10-26T18:53:34.000Z",
    "author": "SunBeltSyndicate",
    "top_comments": []
  },
  {
    "id": "1o4rm13",
    "source": "reddit",
    "subreddit": "r/ragincajuns",
    "title": "17-Unanswered Points Push James Madison Past Louisiana",
    "body": "",
    "url": "https://sunbeltsyndicate.com/17-unanswered-push-james-madison-past-ul-2025/",
    "upvotes": 3,
    "date": "2025-10-12T15:13:15.000Z",
    "author": "SunBeltSyndicate",
    "top_comments": []
  },
  {
    "id": "1ngzfkr",
    "source": "reddit",
    "subreddit": "r/ragincajuns",
    "title": "Is it a good idea to refill water bottle at the soda fountain in the caf?",
    "body": "",
    "url": "https://www.reddit.com/r/ragincajuns/comments/1ngzfkr/is_it_a_good_idea_to_refill_water_bottle_at_the/",
    "upvotes": 3,
    "date": "2025-09-14T18:50:30.000Z",
    "author": "Interesting_Emu5512",
    "top_comments": [
      {
        "text": "Seen plenty of people do it. Don't think anyone would stop you.",
        "upvotes": 6,
        "author": "BrushFireAlpha",
        "date": "2025-09-14T19:27:47.000Z"
      },
      {
        "text": "just don't get caught",
        "upvotes": 2,
        "author": "melodyaura",
        "date": "2025-09-14T20:04:40.000Z"
      },
      {
        "text": "They don’t care\nFew years ago I used to fill a water bottle with chocolate milk and pack spaghetti into a tupper ware (don’t judge me)",
        "upvotes": 1,
        "author": "TraditionalAd5856",
        "date": "2025-09-16T17:18:11.000Z"
      }
    ]
  },
  {
    "id": "1n00t1b",
    "source": "reddit",
    "subreddit": "r/ragincajuns",
    "title": "Join us on Cajun thREDs",
    "body": "Are you looking to talk Ragin' Cajun athletics and more? Then join us on Cajun thREDs. You'll get to engage with a community of individuals that are dedicated to the University of Louisiana Ragin' Cajuns. ",
    "url": "https://cajunthreds.discourse.group/",
    "upvotes": 3,
    "date": "2025-08-25T19:55:20.000Z",
    "author": "CajunRagin77",
    "top_comments": []
  },
  {
    "id": "tpijkd",
    "source": "reddit",
    "subreddit": "r/ApplyingToCollege",
    "title": "Sharing an event my son signed up for. 2nd Annual Virtual College Leadership Fair. Free event",
    "body": "So my son is getting ready to head off to college and he received an invite to this event. I looked it over and it seems like a great idea that should be happening much more. I am sure that there will be a lot of ROTC reps (ROTC is a leadership course at college that you get college credit for while attending college) - I did ROTC when I went to my college…Go UM!! But you do not have to join the military…did it for the elective credit, but looks like this event will have lots of University Admissions and students to help us learn more about opportunities at the schools. Anyways here is the link and the email we got. Good luck future scholars.\n\n[2nd Annual Virtual College Leadership Fair - Free Event](https://urldefense.com/v3/__https://www.eventbrite.com/e/2nd-annual-2022-virtual-college-leadership-fair-tickets-252023989537__;!!FjuHKAHQs5udqho!dDRZ0JX8MNbh-2MD1R3mGQRrjPtzLbNtBtRWYL5bgWfiMfoF-J6nLklSLtedYk8$)\n\nLadies and Gentlmen,\n\n \n\nWelcome to what will be an exciting opportunity for scholars across our country to enage with one another in an extroinary virtual world.  \n\nWhat to expect: 3-Days before the event, you will be e-mailed a link to gain access to our event. Once you enter, you will provde your basic information, and can upload a picture to be used as your icon. You will see hundreds of tables with virtual seats. Simply find the University you are interested in, and click on a seat. You will be brought into a virtual setting where you will be able to see the University reps and they can see you. Dress to Impress! You can choose as many Universities as you want, and each will have information and presentations they can provide you to help you make your best choice. \n\nWhat if I don't want to join Army ROTC? This event is for anyone, so even if you don't want to be apart of the Nations largest leadership trianing team, you can find out more about the University you want to attend.\n\nWhat if I am just a sophmore? We will have experts at the event that can help provide advice on what you can do over the next two years to increase your chances for a National ROTC scholarship to the University of your choice!\n\nWhy would I want an ROTC Scholarship? John Davis recieves a 4 year scholarship to the University of Miami by applying to the National Army ROTC Scholarship. His scholarship covers $25,000 per semester in tuition and fees, pays him $420 a month for being i the program, pays him $600 a semester to cover books in his classes, provides him free Room and Board fees, and allows him to earn elective credits from the program towards his final degree. (Total Scholarship Value over $250,000) - value of overall scholarship depends on University and type of scholarship selected for.\n\nBelow are just a few of the colleges that will be represented at the 2nd Annual College Leadership Fair sponsored by Florida International University Army ROTC.\n\n \n\nSyracuse University\n\nSouthern University and A&amp;amp;amp;M\n\nUniversity of Arkansas at Pines Bluff\n\nHenderson State University\n\nBaptist University\n\nAuburn University\n\nUniversity of Toledo\n\nUniversity of Miami\n\nFlorida International University\n\nNOVA Southeastern University\n\nFlorida Atlantic University\n\nLoyola\n\nDepaul\n\nNorthwestern\n\nUniversity of Idaho\n\nTennessee Technological University\n\nUniversity of North Georgia\n\nUniversity of Tampa\n\nSeton Hall University\n\nUniversity of Wisconsin Stevens Point\n\nUniversity of Wisconsin Stout\n\nUniversity of Wisconsin Eau Claire\n\nUniversity of Wisconsin River Falls\n\nUniversity of Colorado - Colorado Springs\n\nKansas State University\n\nWashington State University\n\nUniversity of Arizona\n\nTexas Tech \n\nRocherster Institute of Technology\n\nSUNY Geneseo\n\nArmy Nursing Program\n\nUniversity of North Alabama\n\nUniversity of Alabama - Birmingham \n\nUniversity of California Los Angeles (UCLA)\n\nBoston College\n\nTexas A&amp;amp;amp;M University\n\nGeorgia Southern University\n\nSavannah State University\n\nMississippi State University\n\nUniversity of Georgia\n\nUniversity of Kansas\n\nFlorida Southern University\n\nEastern Kentucky University\n\nUniversity of North Dakota\n\nIndiana University\n\nUniversity of Texas\n\nWest Virginia State University\n\nFlorida Institute of Technology\n\nCentral State University ROTC\n\nCentral State University ADMISSIONS\n\nUniveristy of Auburn - Montgomery\n\nTroy \n\nUniversity of Maine \n\nWeber State University\n\nUtah State University\n\nTexas A&amp;amp;amp;M - Corpus Christi\n\nMontana State University\n\nUniversity of Washington\n\nGrambling State University\n\nJacksonville State University\n\nCanisius College (University of Buffalo)\n\nLouisiana State University (LSU)\n\nUniversity of Louisiana Lafayette\n\nUniversity of Nebraska - Lincoln\n\nClarkson University\n\nUniversity of Utah\n\nMorgan State University\n\n \n\nWe hope to see you all there!! Please share this event with your friends and family.",
    "url": "https://www.reddit.com/r/ApplyingToCollege/comments/tpijkd/sharing_an_event_my_son_signed_up_for_2nd_annual/",
    "upvotes": 3,
    "date": "2022-03-27T12:03:34.000Z",
    "author": "GrapeEast3181",
    "top_comments": []
  },
  {
    "id": "1syxe30",
    "source": "reddit",
    "subreddit": "r/ragincajuns",
    "title": "Still waiting on MS application decision — anyone else?",
    "body": "Applied to the MS program about 4–5 weeks ago and haven't heard back yet. Graduate school said my application was forwarded to the department, but no email updates since. Is this normal? Anyone else still waiting or have recent experience with the timeline? Would love to know!",
    "url": "https://www.reddit.com/r/ragincajuns/comments/1syxe30/still_waiting_on_ms_application_decision_anyone/",
    "upvotes": 2,
    "date": "2026-04-29T12:29:28.000Z",
    "author": "Few_Lingonberry_267",
    "top_comments": []
  },
  {
    "id": "1r6dci1",
    "source": "reddit",
    "subreddit": "r/ragincajuns",
    "title": "Baseball/Softball tickets",
    "body": "What is the best way to go about buying a single game ticket for a baseball/softball game? Is there still a ticket booth that you can walk up and buy or does it have to be done online? Also, what price is to be expected for a single game? I haven’t been to the Tigue since i was a kid but i live in the area now and it seems like a good way to spend a Saturday night/Sunday.",
    "url": "https://www.reddit.com/r/ragincajuns/comments/1r6dci1/baseballsoftball_tickets/",
    "upvotes": 2,
    "date": "2026-02-16T15:56:27.000Z",
    "author": "Longjumping_Crew_991",
    "top_comments": [
      {
        "text": "it does have to be online but i'd go directly to the UL tickets site. here's the link so you dont have to go searching\nhttps://ragincajuns.evenue.net/",
        "upvotes": 1,
        "author": "the_ozarka_water1",
        "date": "2026-02-16T19:47:34.000Z"
      },
      {
        "text": "Create you an account. I could possible transfer some midweek ⚾ games to you if they aren't being used. Would prob be day b4 or later notice though.",
        "upvotes": 1,
        "author": "CajunDreDog",
        "date": "2026-02-18T03:04:33.000Z"
      }
    ]
  },
  {
    "id": "1oqhcw5",
    "source": "reddit",
    "subreddit": "r/ragincajuns",
    "title": "Cajun Dominance Continue?",
    "body": "History has been kind to Louisiana. The Cajuns have NEVER lost to Texas State. Could that change in the their last Sun Belt matchup Saturday?\n\nKyle Nachtsheim previews the last matchup. ",
    "url": "https://sunbeltsyndicate.com/week-11-preview-texas-state-at-louisiana/",
    "upvotes": 2,
    "date": "2025-11-07T01:32:38.000Z",
    "author": "SunBeltSyndicate",
    "top_comments": []
  },
  {
    "id": "1o8794q",
    "source": "reddit",
    "subreddit": "r/ragincajuns",
    "title": "Week 8 Preview: Southern Miss at Louisiana",
    "body": "In a rivalry recently renewed, now within the Sun Belt, Southern Miss travels to Lafayette to battle the Cajuns. \n\nZac Capps previews this years edition. ",
    "url": "https://sunbeltsyndicate.com/week-8-preview-southern-miss-at-louisiana-2025/",
    "upvotes": 2,
    "date": "2025-10-16T14:13:08.000Z",
    "author": "SunBeltSyndicate",
    "top_comments": []
  },
  {
    "id": "1o3fhks",
    "source": "reddit",
    "subreddit": "r/ragincajuns",
    "title": "Cajuns Travel to Dukes for First Time",
    "body": "What many predicted as a possible Sun Belt Conference championship game, now happens in Week 7. The Cajuns travel to Harrisonburg, VA to take on James Madison.  \n\nDominick Crosetto looks at the first time matchup. ",
    "url": "https://sunbeltsyndicate.com/louisiana-at-james-madison-round-1-2025/",
    "upvotes": 2,
    "date": "2025-10-10T22:47:31.000Z",
    "author": "SunBeltSyndicate",
    "top_comments": []
  },
  {
    "id": "1ncv2h3",
    "source": "reddit",
    "subreddit": "r/ragincajuns",
    "title": "Get in on the excitement at Cajun thREDs",
    "body": "Are you looking to talk Ragin' Cajun athletics and more? Then join us on Cajun thREDs. You'll get to engage with a community of individuals that are dedicated to the University of Louisiana Ragin' Cajuns. We would love to have you you join us and get more support from Acadiana.\n\n[https://cajunthreds.discourse.group/](https://cajunthreds.discourse.group/)",
    "url": "https://www.reddit.com/r/ragincajuns/comments/1ncv2h3/get_in_on_the_excitement_at_cajun_threds/",
    "upvotes": 2,
    "date": "2025-09-09T21:03:07.000Z",
    "author": "CajunRagin77",
    "top_comments": [
      {
        "text": "Can you send a discord invite?",
        "upvotes": 1,
        "author": "[deleted]",
        "date": "2025-09-09T21:21:28.000Z"
      }
    ]
  },
  {
    "id": "1nc6akf",
    "source": "reddit",
    "subreddit": "r/ragincajuns",
    "title": "Reimbursements",
    "body": "Does anyone know when the fafsa reimbursements will be sent for Fall 2025?",
    "url": "https://www.reddit.com/r/ragincajuns/comments/1nc6akf/reimbursements/",
    "upvotes": 2,
    "date": "2025-09-09T01:43:52.000Z",
    "author": "PurfectChicken",
    "top_comments": [
      {
        "text": "If it's from TOPS, then that's in the middle of the semester, around the beginning of October.",
        "upvotes": 1,
        "author": "soccereler",
        "date": "2025-09-09T02:22:01.000Z"
      }
    ]
  },
  {
    "id": "1n06iza",
    "source": "reddit",
    "subreddit": "r/ragincajuns",
    "title": "Need Help",
    "body": "What is this and how do I do it? I thought I submitted everything for my registration before summer. ",
    "url": "https://i.redd.it/ohaz849h59lf1.jpeg",
    "upvotes": 2,
    "date": "2025-08-25T23:43:54.000Z",
    "author": "PurfectChicken",
    "top_comments": [
      {
        "text": "[https://www.sss.gov/register/](https://www.sss.gov/register/)",
        "upvotes": 1,
        "author": "hydraheads",
        "date": "2025-08-25T23:46:34.000Z"
      },
      {
        "text": "UL wants your ass to get drafted boy",
        "upvotes": 1,
        "author": "BrushFireAlpha",
        "date": "2025-08-28T07:33:33.000Z"
      }
    ]
  },
  {
    "id": "1mru020",
    "source": "reddit",
    "subreddit": "r/ragincajuns",
    "title": "Roster Reload - Cajuns",
    "body": "The Ragin Cajuns are the preseason Sun Belt West favorites. Will a new roster, new field, and redone stadium add a new trophy?\n\nGarrett Armbrust takes a look at the Cajuns roster reload.",
    "url": "https://sunbeltsyndicate.com/football-2025-roster-reload-louisiana/",
    "upvotes": 2,
    "date": "2025-08-16T12:34:59.000Z",
    "author": "SunBeltSyndicate",
    "top_comments": []
  },
  {
    "id": "1morcw6",
    "source": "reddit",
    "subreddit": "r/ragincajuns",
    "title": "How to get packages?",
    "body": "Hello, im a freshman and im moving in soon, i was planning on ordering decerations after moving in, so i could get a feel for what i wanted, and what would fit, but now im not sure how recieving packages work, do i just order it to the building im staying in, or are there mail rooms?",
    "url": "https://www.reddit.com/r/ragincajuns/comments/1morcw6/how_to_get_packages/",
    "upvotes": 2,
    "date": "2025-08-13T01:35:09.000Z",
    "author": "Academic_Cod_651",
    "top_comments": [
      {
        "text": "You can get a PO Box from the post office in the union. I’m pretty sure it’s free or pretty cheap",
        "upvotes": 4,
        "author": "The_panda_lord",
        "date": "2025-08-13T01:55:57.000Z"
      }
    ]
  },
  {
    "id": "1m92gtc",
    "source": "reddit",
    "subreddit": "r/ragincajuns",
    "title": "Cajuns Add Talent",
    "body": "Picked to finish first in the West division of the Sun Belt, new transfers look to keep the Cajuns at the top. \n\nOur Cody Slovensky takes a look at the Cajuns biggest additions. ",
    "url": "https://sunbeltsyndicate.com/big-talent-big-promise-louisiana/",
    "upvotes": 2,
    "date": "2025-07-25T15:38:13.000Z",
    "author": "SunBeltSyndicate",
    "top_comments": [
      {
        "text": "Me too.. planning a trip to watch a home game.. gotta go support JJ",
        "upvotes": 2,
        "author": "[deleted]",
        "date": "2025-07-25T19:25:56.000Z"
      },
      {
        "text": "Anybody know what position JJ Garner going to play?",
        "upvotes": 1,
        "author": "[deleted]",
        "date": "2025-07-25T15:43:13.000Z"
      }
    ]
  },
  {
    "id": "1m50bjk",
    "source": "reddit",
    "subreddit": "r/ragincajuns",
    "title": "Is there a freezer attached to the mini fridge in the dorms?",
    "body": "I move into Caronna hall this fall semester, and we're trying to decide if we should buy a fridge or just use the one provided, im wondering if its just a mini fridge or if there is a freezer compartment too?",
    "url": "https://www.reddit.com/r/ragincajuns/comments/1m50bjk/is_there_a_freezer_attached_to_the_mini_fridge_in/",
    "upvotes": 2,
    "date": "2025-07-20T21:14:43.000Z",
    "author": "Academic_Cod_651",
    "top_comments": [
      {
        "text": "When I was a freshman in Bonin in 2017 the fridges did have a little freezer compartment at the top but it wasn’t that great at keeping things frozen",
        "upvotes": 4,
        "author": "thunderkock25",
        "date": "2025-07-20T23:28:24.000Z"
      },
      {
        "text": "There's a small freezer compartment at the top yes but remember that you're splitting that with 3 other people (or 1 if you're in a private style dorm)",
        "upvotes": 3,
        "author": "BrushFireAlpha",
        "date": "2025-07-21T02:56:58.000Z"
      },
      {
        "text": "Yes, there is definitely a freezer but it is quite small, like just enough room for a frozen meal or two, or a couple of ice trays.",
        "upvotes": 2,
        "author": "anyspritely",
        "date": "2025-07-24T13:56:25.000Z"
      },
      {
        "text": "I used to live in Coronna, there was a freezer section in the top of mine but it didn't work. It either melted the frozen items, or if I turned down the temp the items in the fridge section would start to freeze. From what I can tell this isn't common tho, most of the people I knew had both parts working fine.",
        "upvotes": 2,
        "author": "Significant_Cat9899",
        "date": "2025-08-01T01:21:06.000Z"
      },
      {
        "text": "turn it up on da dial",
        "upvotes": 1,
        "author": "gaming-man247",
        "date": "2025-09-27T03:24:24.000Z"
      }
    ]
  },
  {
    "id": "1lu1t2d",
    "source": "reddit",
    "subreddit": "r/ragincajuns",
    "title": "How long did it take to hear back from UL for grad school?",
    "body": "I applied to a graduate program for Fall 2025, and it’s been almost two months since I submitted everything. I’m out of state, so I’m trying to plan ahead in case I need to move.\n\nI’ve called the university twice, but they just told me to keep checking the portal. Another school I applied to has a decision deadline this week, and I’m not sure what to do since I haven’t heard anything from UL yet.\n\nIf you’ve applied to UL for grad school before, how long did it take for you to hear back? Any advice or personal experiences would really help. Thanks!",
    "url": "https://www.reddit.com/r/ragincajuns/comments/1lu1t2d/how_long_did_it_take_to_hear_back_from_ul_for/",
    "upvotes": 2,
    "date": "2025-07-07T18:23:32.000Z",
    "author": "Interesting0801",
    "top_comments": [
      {
        "text": "What did you apply for? \n\nI’m in grad school, I don’t remember how long it took to hear back but it wasn’t quick.",
        "upvotes": 3,
        "author": "cajunbander",
        "date": "2025-07-08T04:51:14.000Z"
      },
      {
        "text": "I just heard back with an update today. I know that they have had issues this year due to some executive orders from the governor, I’m not sure how much that may or may not be affecting each school. I do know that in the spring they had a lot of people end up going to other schools out of state because of the delay.",
        "upvotes": 1,
        "author": "meaux-pie",
        "date": "2025-07-10T19:55:42.000Z"
      },
      {
        "text": "I applied to the M.S. in Accounting program a month ago, but I still haven’t heard back about whether I’ve been accepted. I don’t see why I wouldn’t be. I also applied for a GMAT waiver. Admissions told me they would send my information to the appropriate person for review. Later, I received an email telling me to complete my application.\n\n\n\nAfter following up with the graduate school, I learned that I needed to request the waiver directly from Professor X (for the sake of this conversation). Professor X told me no one had informed her that she needed to review my application. She found others that also needed GMAT waiver reviews.\n\n\n\nA few days later, I received a notification that my GMAT scores were received. Since I never took the GMAT, I followed up with the school. They told me to call the graduate school to confirm whether the waiver had been granted. I called the next day, and they confirmed it had. I’m glad I did, because at that point, they still hadn’t sent my application to the accounting department for review. I had to ask, “When will you send it over?” They told me either later that day or the next day. After the call, I checked again and saw that the status had finally changed to submitted.\n\n\n\nLong story short, make sure they’re actually reviewing your application. They seem overwhelmed, short-staffed, or something.",
        "upvotes": 1,
        "author": "Ok_Break5574",
        "date": "2025-07-31T16:38:24.000Z"
      }
    ]
  },
  {
    "id": "1loctma",
    "source": "reddit",
    "subreddit": "r/ragincajuns",
    "title": "The tectonic plates of the Sun Belt have shifted once again. Who do they look towards next?!",
    "body": "The tectonic plates of the Sun Belt have shifted once again. Who do they look towards next?!\n\nOur Casey Mosrie takes a look at options including; La Tech, ECU, &amp; WKU.",
    "url": "https://sunbeltsyndicate.com/texas-state-approves-pac-12-move/",
    "upvotes": 2,
    "date": "2025-06-30T16:58:18.000Z",
    "author": "SunBeltSyndicate",
    "top_comments": [
      {
        "text": "Texas state got so tired of losing to us they fled the conference 🤣",
        "upvotes": 2,
        "author": "PatrickD0827",
        "date": "2025-06-30T19:24:00.000Z"
      }
    ]
  },
  {
    "id": "1tl1i83",
    "source": "reddit",
    "subreddit": "r/ragincajuns",
    "title": "How experienced do you have to be to join an ensemble?",
    "body": "I’m considering joining an ensemble as a percussionist. I’m interested in the jazz, traditional music, or percussion ensemble. Im not a music major. How much experience are you expected to have and will I be expected to perform as soon as I join? Im a decent drummer, but Im definitely not stage ready. Im sure it varies between each. Any info is appreciated!",
    "url": "https://www.reddit.com/r/ragincajuns/comments/1tl1i83/how_experienced_do_you_have_to_be_to_join_an/",
    "upvotes": 1,
    "date": "2026-05-23T00:53:05.000Z",
    "author": "clobbre-t",
    "top_comments": []
  },
  {
    "id": "1tb7fon",
    "source": "reddit",
    "subreddit": "r/ragincajuns",
    "title": "Free Event! The First Annual Lafayette Community Org Fair is Being Held Friday, May 22nd. Student Orgs Welcome!",
    "body": "",
    "url": "https://www.reddit.com/gallery/1tb7c7g",
    "upvotes": 1,
    "date": "2026-05-12T16:52:37.000Z",
    "author": "Richek_",
    "top_comments": []
  },
  {
    "id": "1sr0ova",
    "source": "reddit",
    "subreddit": "r/ragincajuns",
    "title": "Petroleum Engineering",
    "body": "Any PetE students here? How is the program?",
    "url": "https://www.reddit.com/r/ragincajuns/comments/1sr0ova/petroleum_engineering/",
    "upvotes": 1,
    "date": "2026-04-20T19:49:28.000Z",
    "author": "No-Fill-993",
    "top_comments": []
  },
  {
    "id": "1sm60gc",
    "source": "reddit",
    "subreddit": "r/ragincajuns",
    "title": "Easy Class",
    "body": "This fall will be my last semester and im looking for a class to  my schedule to be full time. something easy so I can focus on my major courses. any suggestions? ",
    "url": "https://www.reddit.com/r/ragincajuns/comments/1sm60gc/easy_class/",
    "upvotes": 1,
    "date": "2026-04-15T13:23:45.000Z",
    "author": "Front_Construction_4",
    "top_comments": [
      {
        "text": "This depends on your major and interests. I always vote for something you’re good at OR something that you’ll want to bite into. Otherwise, a mundane 100-level course will be hard to attend and therefore pass.",
        "upvotes": 1,
        "author": "bigtoe_strongtoe",
        "date": "2026-04-15T23:17:31.000Z"
      },
      {
        "text": "When I was in college slackers took choir.",
        "upvotes": 1,
        "author": "Ok-View-4986",
        "date": "2026-04-16T02:16:33.000Z"
      }
    ]
  },
  {
    "id": "1rlc3uj",
    "source": "reddit",
    "subreddit": "r/ragincajuns",
    "title": "University House Acadiana",
    "body": "So this is my first time noticing the inspection message while living at uhacadiana. just out of curiosity does anyone know if they usually run late? like they gave one date (a Tuesday) and they said if they don't finish the floor by 5 that day they will be back on the second date (the next Thursday) to finish. Do they usually have to use the second date or do they usually finish in one day? Will they leave something to let us know they've been by? I'm just curious.",
    "url": "https://www.reddit.com/r/ragincajuns/comments/1rlc3uj/university_house_acadiana/",
    "upvotes": 1,
    "date": "2026-03-05T08:20:49.000Z",
    "author": "SadRecipe542",
    "top_comments": []
  },
  {
    "id": "1onmmap",
    "source": "reddit",
    "subreddit": "r/ragincajuns",
    "title": "Men's Basketball 2025-26 Roster Reload: Louisiana",
    "body": "",
    "url": "https://sunbeltsyndicate.com/mens-basketball-2025-26-roster-reload-louisiana/",
    "upvotes": 1,
    "date": "2025-11-03T20:14:17.000Z",
    "author": "SunBeltSyndicate",
    "top_comments": []
  },
  {
    "id": "1o0m83v",
    "source": "reddit",
    "subreddit": "r/ragincajuns",
    "title": "Go grant disbursement",
    "body": "I received the go grant and go to University of Louisiana at lafayette but have not received it. I have been told by students that they’ve received their refund on the first day of school but I have yet to receive mine and it’s the beginning of october. When should I expect it to disburse? ",
    "url": "https://www.reddit.com/r/ragincajuns/comments/1o0m83v/go_grant_disbursement/",
    "upvotes": 1,
    "date": "2025-10-07T18:02:14.000Z",
    "author": "Fun_Cabinet_5721",
    "top_comments": [
      {
        "text": "You should contact the financial aid office to see when that is set to disburse to your account. Once that post to your account, the bursar can issue your refund.",
        "upvotes": 3,
        "author": "Aggressive_Hawk_8338",
        "date": "2025-10-07T19:40:40.000Z"
      },
      {
        "text": "Mine just disappeared from my account. I think that means it just got refunded.",
        "upvotes": 1,
        "author": "Drawer-Weird",
        "date": "2025-11-07T16:41:26.000Z"
      }
    ]
  },
  {
    "id": "1mkovja",
    "source": "reddit",
    "subreddit": "r/ragincajuns",
    "title": "Parking Alternatives? First Time Freshman",
    "body": "Hi! Besides paying the $360ish for the semester parking tower pass, does anyone know any cheaper alternatives to park? I won’t be living on campus and will be going to school Monday through Friday from about 9am-1pm. My dms are open is anyone wants to talk too! ",
    "url": "https://www.reddit.com/r/ragincajuns/comments/1mkovja/parking_alternatives_first_time_freshman/",
    "upvotes": 1,
    "date": "2025-08-08T07:33:29.000Z",
    "author": "PurfectChicken",
    "top_comments": [
      {
        "text": "You can park at Cajun Field and get the shuttle for free. If you're on campus for a chunk of time and don't need to come and go, that's the best option.",
        "upvotes": 5,
        "author": "DrunkPenguinArmy",
        "date": "2025-08-08T13:16:10.000Z"
      },
      {
        "text": "Taking the shuttle from cajun field is actually pretty nice, it gives you a few minutes to check emails and whatnot before class. Only takes like 5-10 minutes tops",
        "upvotes": 3,
        "author": "BrushFireAlpha",
        "date": "2025-08-08T16:07:17.000Z"
      },
      {
        "text": "Theres no more shuttle service from cajun field?\n\nIf you have a buddy that lives close by, park at their house. Idk how strict the edge is now but could park there and take their shuttle until caught lol",
        "upvotes": 1,
        "author": "Aggressive_Hawk_8338",
        "date": "2025-08-08T11:40:53.000Z"
      }
    ]
  },
  {
    "id": "1lvmi89",
    "source": "reddit",
    "subreddit": "r/ragincajuns",
    "title": "Sun Belt Football Seasons That Defined a Legacy of Excellence",
    "body": "Since 2001, Sun Belt football has delivered powerhouse seasons that punched above their weight—App State, Coastal, Louisiana, and Troy all proved they could hang with the nation's best. Our Kyle Nachtsheim looks back at five campaigns that redefined the Sun Belt football landscape.",
    "url": "https://sunbeltsyndicate.com/dominant-sun-belt-seasons-that-defined/",
    "upvotes": 1,
    "date": "2025-07-09T15:59:23.000Z",
    "author": "SunBeltSyndicate",
    "top_comments": []
  },
  {
    "id": "1ua5t92",
    "source": "reddit",
    "subreddit": "r/ragincajuns",
    "title": "Louisiana Ragin' Cajuns 2026 Football Team Preview",
    "body": "We recently sat down with Dawson Eisherloh, Host of the Loh Down for ESPN – SW Louisiana &amp; Sideline Reporter for Ragin’ Cajun Football, to preview the 2026 Louisiana Ragin' Cajuns Football Team. Here is a link to the video if you are interested in hearing more! [2026 Louisiana Ragin' Cajuns Football Team Preview](https://www.youtube.com/watch?v=jViq6VHqTw4)\n\nIf you are looking for MORE G6 College Football Content Check Out our [YouTube Page](https://www.youtube.com/@G5Hive) and follow us on [X/Twitter](https://x.com/G5Hive)! Episodes are also available on  [Amazon Music](https://music.amazon.in/podcasts/da3cad9b-26b8-4a9e-b83a-ad8c9bd08df1/the-g5-hive), [Apple Podcasts](https://podcasts.apple.com/gb/podcast/the-g5-hive/id1704591509) and [Spotify](https://open.spotify.com/show/4Sd5XzJCLYiAcf18OGIzc3) if you rather listen in audio form.",
    "url": "https://www.reddit.com/r/ragincajuns/comments/1ua5t92/louisiana_ragin_cajuns_2026_football_team_preview/",
    "upvotes": 0,
    "date": "2026-06-19T15:58:28.000Z",
    "author": "TheG5Hive",
    "top_comments": []
  },
  {
    "id": "1lyfxf6",
    "source": "reddit",
    "subreddit": "r/ragincajuns",
    "title": "Color Opinion",
    "body": "Chat which Macbook color better - space black or silver?",
    "url": "https://www.reddit.com/r/ragincajuns/comments/1lyfxf6/color_opinion/",
    "upvotes": 0,
    "date": "2025-07-13T00:53:15.000Z",
    "author": "Forward_Guarantee541",
    "top_comments": [
      {
        "text": "Space black",
        "upvotes": 4,
        "author": "Different_Watch_465",
        "date": "2025-07-13T03:28:53.000Z"
      },
      {
        "text": "Space black.",
        "upvotes": 1,
        "author": "cajunsurvivorguy",
        "date": "2025-08-25T22:09:11.000Z"
      }
    ]
  },
  {
    "id": "1llx4x7",
    "source": "reddit",
    "subreddit": "r/ragincajuns",
    "title": "Conference",
    "body": "Why are there no talks of UL trying to get out of sun belt? Texas state leaving hurts and I feel like a move to a conference like the big 12 would greatly benefit athletic funding to an already relatively good athletics program.",
    "url": "https://www.reddit.com/r/ragincajuns/comments/1llx4x7/conference/",
    "upvotes": 0,
    "date": "2025-06-27T15:42:41.000Z",
    "author": "Typical_Tale4482",
    "top_comments": [
      {
        "text": "Nah the sunbelt has done a great job of reinvesting in itself over the past few years. I’d much rather us be in a conference that has some geographical ties left and teams that are competitive on our level than go to some random p5 just for a couple more widely televised games a year",
        "upvotes": 5,
        "author": "PatrickD0827",
        "date": "2025-06-27T15:58:44.000Z"
      },
      {
        "text": "Who’s to say that a more prestigious conference would want us? I saw some talk on r/cfb of us having an outside chance of joining the Big 12 in the mid future, but our profile still probably needs improvement before a power conference would think we bring something to the table.",
        "upvotes": 1,
        "author": "ramblingMess",
        "date": "2025-06-27T16:35:49.000Z"
      }
    ]
  }
]