{
  "housing": {
    "key_points": [
      "Dorm conditions historically poor; dirty bathrooms explicitly called out",
      "Thieving roommates flagged in a viral honest campus tour video",
      "Alumni note major upgrades since early 2000s, but baseline still rough"
    ],
    "key_quotes": [
      "DIRTY BATHROOMS?? THIEVING ROOMMATES?",
      "it was better than the Towers back in the early 90s. It was some nasty ass heffas in them dorms!!",
      "Once u gone tho, u gonna miss certain memories. But at and during that moment...it IS TOUGH!!"
    ],
    "score": 4
  },
  "social_life": {
    "key_points": [
      "Band culture and Greek life are the undisputed social heartbeat of campus",
      "Stroll-offs, Battle of the Greeks, and homecoming are major recurring events",
      "Social scene is vibrant but heavily tied to Greek orgs and band community"
    ],
    "key_quotes": [
      "9/10/20 this came across my feed. Took me back to my NSU days. Makes me wanna come back for homecoming again.",
      "That's why I love HBCU bands. You get a pre-game show, a half-time show and a post-game show.",
      "Q's was tripping they did practice... come on brother"
    ],
    "score": 8
  },
  "dining": {
    "key_points": [
      "Almost zero student commentary on dining quality from either source",
      "Campus tour notes a cafe in the library as an upgrade alumni appreciated",
      "Dining workers rallied for unionization — suggests labor tension in food services"
    ],
    "key_quotes": [
      "Cafe in the library??? and fitness center in the student union now... I am so glad I see my money has went to awesome upgrades!",
      "Norfolk State University dining workers rally for unionization"
    ],
    "score": 5
  },
  "mental_health": {
    "key_points": [
      "Counseling Center runs active programming including journaling groups and yoga",
      "Self-Care Day events with free food signal institutional awareness of student stress",
      "No student complaints or praise about counseling quality — usage unclear"
    ],
    "key_quotes": [
      "NSU Counseling Center Wellness Week — Break, Scatter, Transform: Grief into Meaning",
      "Spring Refresher: Self-Care Day — Mental wellness tips, DIY self-care kits, journaling and vision boarding",
      "Share Your Voice to Improve Mental Health Research for Black and Latino youth"
    ],
    "score": 6
  },
  "financial_aid": {
    "key_points": [
      "No direct student complaints about NSU financial aid in the data",
      "Scholarships and fellowships actively promoted on campus subreddit",
      "Tuition competitiveness frequently cited as a reason students consider NSU"
    ],
    "key_quotes": [
      "NSU Students - Paid E-Mobility Fellowship Now Open",
      "Thurgood Marshall College Fund Info Session at NSU — scholarships, internships, and the Leadership Institute",
      "Behold the Green and Gold — [alumni proud of where their money went in campus upgrades]"
    ],
    "score": 6
  },
  "academics": {
    "key_points": [
      "One student reports a hard macroeconomics course dragging down an otherwise strong GPA",
      "Masters program in electronics engineering noted as unique in Virginia — a niche draw",
      "Cyberpsychology grad program exists, suggesting some specialized academic offerings"
    ],
    "key_quotes": [
      "I took it a regular semester in person with Dr. Kamiru, I actually liked his class and felt like I learned a lot but I made a C+, the tests were hard.",
      "NSU is the only one that has that [electronics engineering masters] program in Virginia",
      "Is anyone currently in a masters program for Cyberpsychology?"
    ],
    "score": 6
  },
  "administration": {
    "key_points": [
      "No specific horror stories about NSU admin, but data is thin overall",
      "r/NorfolkState subreddit is newly active — suggests limited community infrastructure",
      "Dining worker unionization push hints at management-labor friction behind the scenes"
    ],
    "key_quotes": [
      "Welcome to r/NorfolkState — This is a space for the NSU community to connect.",
      "Norfolk State University dining workers rally for unionization",
      "HITT Contracting Inc. is coming to campus for a Table Talk — [career events suggest active career services engagement]"
    ],
    "score": 5
  },
  "location_and_campus": {
    "key_points": [
      "Campus has seen significant upgrades since the 2000s — alumni consistently note improvement",
      "Norfolk 757 area inspires strong regional pride among students and locals",
      "No complaints about location; proximity to Hampton Roads seen as a plus"
    ],
    "key_quotes": [
      "They did so much to the campus since 00-04... I am so glad I see my money has went to awesome upgrades!",
      "I've watched this video so many times... living in the 757 area I am so proud of you all",
      "I took a tour of the campus while I was at the AAU track and field nationals this summer, and I loved it."
    ],
    "score": 7
  },
  "career_outcomes": {
    "key_points": [
      "Wells Fargo, HITT Contracting, and Thurgood Marshall Fund recruit directly on campus",
      "NFL draft history is thin — last player drafted was 2009, per Reddit post",
      "HBCU alumni network and brand recognized but NSU specifically not called out as a career powerhouse"
    ],
    "key_quotes": [
      "2009 is the last time a player has made it into the NFL",
      "Wells Fargo is coming to campus for an Early Career Info Session — internships, full time roles",
      "NSU just hired Michael Vick as the Spartans Football head coach — [raises profile but football success TBD]"
    ],
    "score": 5
  },
  "value_for_money": {
    "key_points": [
      "Cost of attendance cited as competitive compared to Virginia PWIs",
      "Scholarships appear accessible — multiple fellowship and funding opportunities posted",
      "No student reports of financial aid disasters or hidden fee shocks specific to NSU"
    ],
    "key_quotes": [
      "NSU is the only one that has that program in Virginia — [unique program justifies cost for some]",
      "Paid E-Mobility Fellowship — monthly stipend, research and publication opportunities",
      "I am so glad I see my money has went to awesome upgrades!"
    ],
    "score": 6
  },
  "overall_vibe": {
    "key_points": [
      "Band and performance culture is elite — nationally recognized, inspires genuine awe worldwide",
      "Strong HBCU pride and community identity define the NSU experience",
      "Small but loyal student community; campus life is real but not hyped on mainstream platforms"
    ],
    "key_quotes": [
      "This is the video that made my daughter chose NSU when she was a senior in high school in 2021. Now she is a part of the Spartan Legion!!!",
      "Norfolk State University was legendary to us back then... Still absolute legends. When I want to inspire him with badassery, I send him NSU videos.",
      "I'm British and never seen anything like this before. It gave me chills."
    ],
    "score": 7
  },
  "red_flags": {
    "key_points": [
      "Housing: dirty bathrooms and roommate theft flagged in honest campus tour video",
      "Athletics: no NFL draft pick since 2009, football program historically weak",
      "Administration: dining worker unionization push signals possible institutional dysfunction"
    ],
    "key_quotes": [
      "DIRTY BATHROOMS?? THIEVING ROOMMATES?",
      "2009 is the last time a player has made it into the NFL",
      "Norfolk State University dining workers rally for unionization"
    ],
    "score": 5
  },
  "hidden_gems": {
    "key_points": [
      "Spartan Legion band is a legitimate national-level attraction — a real recruiting draw",
      "Unique graduate programs like electronics engineering and cyberpsychology hard to find elsewhere in VA",
      "Active career pipeline events with major employers happening regularly on campus"
    ],
    "key_quotes": [
      "One of the most underrated bands in the US!! they are dead on it every time",
      "NSU is the only one that has that [electronics engineering masters] program in Virginia",
      "The Legion did its thing and the crowd loved it. Many were in awe. One woman near me had her mouth was wide open."
    ],
    "score": 8
  }
}