[
  {
    "id": "Ugw2-_G2GTptog2TV2p4AaABAg",
    "source": "youtube",
    "title": "First Day Of My University In Uk|York St. John University 🇬🇧",
    "body": "Kasto Maya lagyo yar timro Ghar ma Huda khane Kura ko matlab hunthena Bidesh Gaye pachi Khana lai Pani parkhinu parcha 😢keep working hard sister lots of love ❤️❤️",
    "upvotes": 6,
    "date": "2023-09-22T15:07:50Z",
    "author": "@bikashsharma2983"
  },
  {
    "id": "Ugz77OD2DzjeVtgguPh4AaABAg",
    "source": "youtube",
    "title": "First Day Of My University In Uk|York St. John University 🇬🇧",
    "body": "Ronisha sis, college Jada ghar bata khana ya khaja lunch bokera janu parcha tiffin mah, natra sadai baira khada ra canteen mah ekdum expensive ra kharcha dherai huncha starting mah.. so pack some food in the morning ani university ko microoven mah ya byanai khada pani huncha free time mah, paisa dherai saving huncha yesto Garda..",
    "upvotes": 10,
    "date": "2023-09-22T13:56:58Z",
    "author": "@chanzyonzan3044"
  },
  {
    "id": "Ugw0EJLyOOHQHGGwOpx4AaABAg",
    "source": "youtube",
    "title": "First Day Of My University In Uk|York St. John University 🇬🇧",
    "body": "nepalko khana kati miss gariracha bhai ra bainiharule,  video hrera enjoy garirachu baini,  yestai yestai afnai nepali parako vlogs herda nepali fill huncha , aba next heraula.",
    "upvotes": 2,
    "date": "2023-09-22T18:40:12Z",
    "author": "@partapkc2082"
  },
  {
    "id": "UgyG2CH-kTdta38upP14AaABAg",
    "source": "youtube",
    "title": "First Day Of My University In Uk|York St. John University 🇬🇧",
    "body": "Dont feel boring everytime is not a sunday.i know you can do it Ronisha its  part of life.yo tah trailers ho picture toh abhibaki hai you don&#39;t need to worry we always with you cute couple ever keep loving keep vloging❤❤❤❤",
    "upvotes": 7,
    "date": "2023-09-22T23:15:57Z",
    "author": "@gabbarrai5327"
  },
  {
    "id": "Ugy8-isZdzFiEMC22414AaABAg",
    "source": "youtube",
    "title": "കർണാടകാ നഴ്‌സിംഗ് അഡ്മിഷൻ… ചതി തിരിച്ചറിയുക I About st john&#39;s college of nursing",
    "body": "നമ്മുടെ കൊച്ചുകേരളത്തിൽ, no 1കേരളത്തിൽ ഇങ്ങനെയുള്ള സ്ഥാപനങ്ങൾ ഇല്ലാത്തതുകൊണ്ടും സർക്കാർ അതിനുള്ള സൗകര്യം ഉണ്ടാക്കി കൊടുക്കാത്തതുകൊണ്ടുമല്ലേ നമ്മുടെ ലക്ഷങ്ങൾ മറ്റു സ്റ്റേറ്റുകാർ കൊണ്ടുപോകുകയും അതുവഴി നമ്മുടെ കുട്ടികൾ കബളിപ്പിക്കപ്പെടുന്നതും. എന്ത് ചെയ്യാം.",
    "upvotes": 11,
    "date": "2026-04-30T11:34:15Z",
    "author": "@SubashV-wf1vu"
  },
  {
    "id": "UgyKv5g2Y_D5tKQn-VJ4AaABAg",
    "source": "youtube",
    "title": "കർണാടകാ നഴ്‌സിംഗ് അഡ്മിഷൻ… ചതി തിരിച്ചറിയുക I About st john&#39;s college of nursing",
    "body": "ഞങ്ങൾ അവിടെ ഗൈഡൻസിന് പോയിരുന്നു. വളരെ ഉപകാരപ്രദമായ അനുഭവമായിരുന്നു. കോഴ്സുമായി ബന്ധപ്പെട്ട എല്ലാ സംശയങ്ങളും വ്യക്തമായി മറുപടി ലഭിച്ചു. വളരെസഹായകരമായിരുന്നു.ഞങ്ങൾ കഴിഞ്ഞ വർഷം അഡ്മിഷൻ എടുത്തത് ഇപ്പഴും അവരായിട്ട് കോൺടാക്ട് ഉണ്ട്.",
    "upvotes": 3,
    "date": "2026-05-01T08:22:38Z",
    "author": "@Sijias"
  },
  {
    "id": "UgxoAI1mneAEhUA-mmZ4AaABAg",
    "source": "youtube",
    "title": "കർണാടകാ നഴ്‌സിംഗ് അഡ്മിഷൻ… ചതി തിരിച്ചറിയുക I About st john&#39;s college of nursing",
    "body": "With 25 years of experience as an educational consultant in Bangalore, I would like to share an important observation. So far, I have not handled any admissions for St. John&#39;s Medical College, as their admission process is strictly based on merit.<br>However, I have noticed that many parents do not personally visit colleges or take sufficient time to plan their children’s future. Instead, they often rely on unverified sources and end up handing over money to untrustworthy channels.<br>At the same time, it is important to recognize that there are also many genuine and trusted consultants who guide students and parents in the right direction. Choosing the right and reliable consultant is crucial for ensuring a safe and transparent admission process.",
    "upvotes": 6,
    "date": "2026-04-30T10:11:29Z",
    "author": "@BANGALOREEDU"
  },
  {
    "id": "Ugz6ytNCXbYcsYsR1kR4AaABAg",
    "source": "youtube",
    "title": "കർണാടകാ നഴ്‌സിംഗ് അഡ്മിഷൻ… ചതി തിരിച്ചറിയുക I About st john&#39;s college of nursing",
    "body": "സെന്റ് ജോൺസൺ ഹോസ്പിറ്റലിൽ പുറമേന്ന് ഏജൻസികൾക്ക് അവിടെ അഡ്മിഷൻ കൊടുക്കാറില്ല കുറച്ചു സീറ്റ് മാത്രമേ അവിടെ ഉണ്ടാകാറുള്ളൂ മെറിറ്റ് അടിസ്ഥാനത്തിലാണ് അഡ്മിഷൻ നടത്തുന്നത് ഈ ചതിയിൽ ആരും പോയി പെടരുത് ഇതുപോലെ തന്നെ  ഈ വീഡിയോയിൽ പറഞ്ഞ മറ്റ് ഹോസ്പിറ്റലുകളും 🙏",
    "upvotes": 8,
    "date": "2026-04-30T17:11:09Z",
    "author": "@salimonmadhavan7243"
  },
  {
    "id": "UgzUu8OPfTu_FNudtSd4AaABAg",
    "source": "youtube",
    "title": "കർണാടകാ നഴ്‌സിംഗ് അഡ്മിഷൻ… ചതി തിരിച്ചറിയുക I About st john&#39;s college of nursing",
    "body": "Thank you Ma&#39;am Bindu and the channel. I hope this will help many aspiring candidates and parents. <br>I am proud of my institution. It stands for its ethics and stands for integrity, compassion and excellence",
    "upvotes": 0,
    "date": "2026-04-30T16:32:25Z",
    "author": "@littivictoriakavungal8030"
  },
  {
    "id": "UgyFfen08PVgIVuflXl4AaABAg",
    "source": "youtube",
    "title": "കർണാടകാ നഴ്‌സിംഗ് അഡ്മിഷൻ… ചതി തിരിച്ചറിയുക I About st john&#39;s college of nursing",
    "body": "നഴ്സിങ് എന്ന് മാത്രമല്ല ഒരു കോഴ്‌സിനും ഏതെങ്കിലും കൺസൾട്ടൻസി പറയുന്നത് കേട്ട് അഡ്‌മിഷന് പൈസ ചാടിക്കയറി കൊടുക്കരുത്. അതാതു സ്ഥാപനങ്ങളെ കോണ്ടാക്ട്  ചെയ്ത് സത്യാവസ്ഥ ഉറപ്പു വരുത്തുകയാണ് ആദ്യം ചെയ്യേണ്ടത്. തട്ടിക്കൂട്ട് കൺസൾട്ടൻസികൾ ഒരുപാടുണ്ട് നമ്മുടെ രാജ്യത്ത്. ചൈനയിൽ പൈലറ്റ് ട്രെയിനിങ് പഠിക്കാൻ അഡ്മിഷൻ റെഡി ആക്കി തരാം എന്ന് പറഞ്ഞ് ചൈനയിൽ നൂഡിൽസ് ഉണ്ടാക്കാൻ പഠിപ്പിക്കുന്ന കോഴ്‌സിന് വിടുന്ന ഏജൻസികളും ഇവിടെ ധാരാളമുണ്ട്😀😀",
    "upvotes": 10,
    "date": "2026-04-30T09:42:28Z",
    "author": "@AlanAlan-d8c"
  },
  {
    "id": "UgxmfpFE8kbrGMmQnxB4AaABAg",
    "source": "youtube",
    "title": "കർണാടകാ നഴ്‌സിംഗ് അഡ്മിഷൻ… ചതി തിരിച്ചറിയുക I About st john&#39;s college of nursing",
    "body": "കർണാടകയിൽ നേഴ്സിങ് പഠിക്കാൻ പോകുമ്പോൾ മെയിൻ ആയിട്ട് ശ്രദ്ധിക്കേണ്ട കാര്യം ഐ എൻ സി അംഗീകാരം ഉള്ള കോളേജ് ആണോ എന്ന് എന്നുള്ളതാണ്... ഒരു കോളേജിന് പൊറ്റ നേഴ്സിങ് കോളേജ് ഉള്ളോ എന്നുള്ളത് കറക്റ്റ് ആയിട്ട് ശ്രദ്ധിക്കണം.. എന്റെ മകനെ കർണാടകയിൽ പഠിക്കാൻ വിട്ടപ്പോൾ എനിക്ക് അബദ്ധം പറ്റിയതാണ്.. ഗ്രൂപ്പ് ഓഫ് ഇൻസ്റ്റിറ്റ്യൂഷൻ എന്നും എടുക്കുകയും എക്സാം ടൈം ഹാൾടിക്കറ്റ് കൊടുത്തപ്പോൾ വേറൊരു കോളേജിലാണ് അവന്റെ പേര് രജിസ്റ്റർ ചെയ്തിരിക്കുന്നത് കോളേജിന് ഐഎസി ഉള്ളതാണ് മാരുടെ വലയിൽ പെടാതെ സൂക്ഷിക്കുക",
    "upvotes": 7,
    "date": "2026-04-30T09:39:13Z",
    "author": "@rengannan"
  },
  {
    "id": "UgwJufbw9AYJaSRd5m54AaABAg",
    "source": "youtube",
    "title": "കർണാടകാ നഴ്‌സിംഗ് അഡ്മിഷൻ… ചതി തിരിച്ചറിയുക I About st john&#39;s college of nursing",
    "body": "കേരളത്തിൽ ഉള്ള കോളേജുകളിൽ ശരിയായ രീതിയിൽ നിയമനം നടത്തിയാൽ ഈ പ്രശ്നത്തിനു പരിഹാരം ഉണ്ടാക്കാം. നമ്മുടെ ഗവണ്മെന്റ് ഇതിൽ ശക്തിയായി ഇടപെടണം. അനുഭവം ഉള്ളത് കൊണ്ട് പ്രതികരിച്ചതാണ്.ഇനി വരുന്ന വിദ്യാർഥികൾക്കെങ്കിലും പ്രയോജനം ആകട്ടെ 🙏",
    "upvotes": 1,
    "date": "2026-05-01T06:40:56Z",
    "author": "@bindumanoj6971"
  },
  {
    "id": "UgxvaeLTiQlXH3m1et14AaABAg",
    "source": "youtube",
    "title": "കർണാടകാ നഴ്‌സിംഗ് അഡ്മിഷൻ… ചതി തിരിച്ചറിയുക I About st john&#39;s college of nursing",
    "body": "Ithoke ulliloode nadakunundaavum, ithipo advertisement aayi vannathukondu avar naturally ethirkum,  kaashu vangikunnathu aarengilum thurannu sammathikumo,  ithu management schoolil teacher job sure aakunnapoleyaanu, management ennengilum kashu medikunnathu sammathichitundo",
    "upvotes": 0,
    "date": "2026-05-01T08:10:51Z",
    "author": "@Gazab251"
  },
  {
    "id": "UgwTsxHgAas2xbPUend4AaABAg",
    "source": "youtube",
    "title": "The WORST Parts About St. John&#39;s University - Campus Interviews - LTU",
    "body": "Check out some of the other videos on this channel for more interesting conversations!<br>What are your thoughts on these students views? Do you want to be a student at St. John&#39;s University?",
    "upvotes": 7,
    "date": "2019-04-11T03:49:31Z",
    "author": "@LetsTalkUniversity"
  },
  {
    "id": "UgxNTTLPtXZXcOw4u0p4AaABAg",
    "source": "youtube",
    "title": "The WORST Parts About St. John&#39;s University - Campus Interviews - LTU",
    "body": "I&#39;m a commuting senior here, the worst part is the expensive tuition. I&#39;m in a low income family and even after all the aid and scholarship, I still have to pay around 12k with single parent. The location not great either. Commuting through Jamaica, you sometimes gets harassed and met by rude and violent people",
    "upvotes": 50,
    "date": "2022-05-07T14:02:24Z",
    "author": "@VernariaTofu"
  },
  {
    "id": "UgwF7P4pqovteaVm3mV4AaABAg",
    "source": "youtube",
    "title": "The WORST Parts About St. John&#39;s University - Campus Interviews - LTU",
    "body": "interesting how this stuff hasn&#39;t changed... where is the money that the school gets? why aren&#39;t there more support for commuter students?",
    "upvotes": 3,
    "date": "2024-09-01T00:08:31Z",
    "author": "@amazingsunsets103"
  },
  {
    "id": "Ugz8-KidAt9DnstYZrh4AaABAg",
    "source": "youtube",
    "title": "The WORST Parts About St. John&#39;s University - Campus Interviews - LTU",
    "body": "Suny Oswego graduate here. St. John’s University was one of my colleges I picked to attend when I graduated from high school.",
    "upvotes": 4,
    "date": "2022-08-22T03:19:23Z",
    "author": "@andrewjones2133"
  },
  {
    "id": "UgxLwijosEJIjHPKwct4AaABAg",
    "source": "youtube",
    "title": "The WORST Parts About St. John&#39;s University - Campus Interviews - LTU",
    "body": "I went to si campus late 80s.  It was a very small campus. We had the newspaper, campus announcements, and more.",
    "upvotes": 6,
    "date": "2021-10-17T23:40:10Z",
    "author": "@arfriedman4577"
  },
  {
    "id": "Ugw1nrea_hISJPkuQm14AaABAg",
    "source": "youtube",
    "title": "The WORST Parts About St. John&#39;s University - Campus Interviews - LTU",
    "body": "The bad grades I get ? That’s your fault not the school unless everyone knows that class is hard to get a good grade in",
    "upvotes": 23,
    "date": "2019-12-22T19:59:56Z",
    "author": "@boostedboosted3088"
  },
  {
    "id": "UgzLrtG_GQQhaXMUlJ54AaABAg",
    "source": "youtube",
    "title": "The WORST Parts About St. John&#39;s University - Campus Interviews - LTU",
    "body": "@<a href=\"https://www.youtube.com/watch?v=ZiEA5DE9lJk&amp;t=214\">3:34</a> what point is she trying to make lmao. Of course they won’t tell if you don’t ASK. Plus you’re in college, you’re not a child anymore of course you need to figure things out on your own.",
    "upvotes": 18,
    "date": "2021-01-01T01:38:47Z",
    "author": "@cailivestreams"
  },
  {
    "id": "UgyxtDFBdvUL8ut5ZxZ4AaABAg",
    "source": "youtube",
    "title": "The WORST Parts About St. John&#39;s University - Campus Interviews - LTU",
    "body": "...I commuted there from Williamsburg Brooklyn for 5 years...2 subways (GG &amp; E or F train) and a bus to Union Turnpike &amp; Utopia...pharmacy major 78&#39;...don&#39;t know how I did it...",
    "upvotes": 1,
    "date": "2023-04-19T17:13:23Z",
    "author": "@benjaminhogan3157"
  },
  {
    "id": "UgxXnKLOmeSleMSB-Rd4AaABAg",
    "source": "youtube",
    "title": "The WORST Parts About St. John&#39;s University - Campus Interviews - LTU",
    "body": "Shallow students...they are suppose to draw on the wisdom of their elders and apply the knowledge using their way of thinking instead of complaining &quot;lack of diversity&quot;  woah woah woah.<br><br>To that young lady in white jacket @ <a href=\"https://www.youtube.com/watch?v=ZiEA5DE9lJk&amp;t=178\">2:58</a>, as a graduate of this school as a Redman, philosophy will serve her well.  It did for me even now.<br><br>I graduated from this school some time ago and diversity is NOT what&#39;s lacking.",
    "upvotes": 6,
    "date": "2023-02-17T06:32:03Z",
    "author": "@nmssis"
  },
  {
    "id": "Ugzc7UA3VM-rN4JVSKp4AaABAg",
    "source": "youtube",
    "title": "The WORST Parts About St. John&#39;s University - Campus Interviews - LTU",
    "body": "Not great. St.Johns is very diverse, students and professors. Depends on your major as well. School President is Filipino. The dorms are only 20 yrs old. That’s fairy new compared to other schools. St. John’s gives a ton of AID. The problem is St. John’s allows too many folks in that have no business in school along with putting them into debt. I would say majority of ppl you interviewed would be better off at CUNY school. Also the complaint you have to take Theology, it’s fucking a Catholic school! They offer other religions, the school goes out of its way. If the school took academics much more serious kicked out riff raff, St.John’s could be Fordham.",
    "upvotes": 17,
    "date": "2020-04-04T13:18:10Z",
    "author": "@Youknowit86"
  },
  {
    "id": "UgzN8Hsp9XBborpNlM94AaABAg",
    "source": "youtube",
    "title": "My HONEST UNIVERSITY EXPERIENCE at a &quot;TOP&quot; UK UNIVERSITY | York St John and Bristol University",
    "body": "i&#39;m very happy you decided to start your channel here on YouTube because i love all your videos. you are so lovely to watch and i especially love how you don&#39;t pull any punches when you are expressing how you feel about something, i love the raw honesty :-)",
    "upvotes": 6,
    "date": "2020-08-11T11:59:27Z",
    "author": "@JesusLovesYouPerfectly"
  },
  {
    "id": "Ugw6LYF53GiVR2Mj8bJ4AaABAg",
    "source": "youtube",
    "title": "My HONEST UNIVERSITY EXPERIENCE at a &quot;TOP&quot; UK UNIVERSITY | York St John and Bristol University",
    "body": "What an amazing report!<br>I can yet understand the reasons why you are the kind of good teacher you are.<br>Continue being yourself, keep being happy teaching us, and best wishes, Emma!",
    "upvotes": 4,
    "date": "2021-09-12T20:24:00Z",
    "author": "@xabiermartinez1952"
  },
  {
    "id": "UgxyC3ZJOfI7Ze5hW4l4AaABAg",
    "source": "youtube",
    "title": "My HONEST UNIVERSITY EXPERIENCE at a &quot;TOP&quot; UK UNIVERSITY | York St John and Bristol University",
    "body": "You are hardworking, you deserve the best. I really enjoyed your video. It motivates me to move forward on my studies.",
    "upvotes": 4,
    "date": "2019-12-21T18:23:25Z",
    "author": "@Mikael97"
  },
  {
    "id": "UgwnOhpIyxMxOgakIy54AaABAg",
    "source": "youtube",
    "title": "My HONEST UNIVERSITY EXPERIENCE at a &quot;TOP&quot; UK UNIVERSITY | York St John and Bristol University",
    "body": "Emma, I am so glad that you started your youtube channel because you wouldn&#39;t have made this video if you hadn&#39;t. It was really great to learn about your university experience. I didn&#39;t go to university because the degree I took after I gratuated was still in high school in my city. So no big changes for me. You have so great experience in both your universities and in Spain. It was very great to listen to you during those 30 minutes. Thanks for sharing with us.",
    "upvotes": 1,
    "date": "2023-12-03T20:17:37Z",
    "author": "@helener7101"
  },
  {
    "id": "Ugzw88VEZ9r-T_l31x94AaABAg",
    "source": "youtube",
    "title": "My HONEST UNIVERSITY EXPERIENCE at a &quot;TOP&quot; UK UNIVERSITY | York St John and Bristol University",
    "body": "Thanks very much, I feel that we have the same experience with some teachers and classmates. It&#39;s very important never give up.",
    "upvotes": 4,
    "date": "2019-11-22T23:17:32Z",
    "author": "@noemialsur255"
  },
  {
    "id": "UgxV23h2DFvA3vJV_IZ4AaABAg",
    "source": "youtube",
    "title": "My HONEST UNIVERSITY EXPERIENCE at a &quot;TOP&quot; UK UNIVERSITY | York St John and Bristol University",
    "body": "Emma, thank you for sharing your experience at universities in the UK. It was quite interesting. In Japan, there are also a lot of arguments on the university ranking. I think most of the indices used for the evaluation rely on the visible outcomes like the number of publications, the scale of budget income, and so on. I personally believe the caring for the students in various senses should be the priority, even it is hard to evaluate by numerical indices. I am glad to hear your honest opinion. It was a really good reminder for me, as a lecturer in a university (I never recommend using Google in my class, though). By the way, your RP videos are quite helpful to set my Japanese-English tongue right. I&#39;ll keep watching.",
    "upvotes": 6,
    "date": "2020-09-29T21:52:17Z",
    "author": "@SilverUK-f9y"
  },
  {
    "id": "UgzfY60GHu0itV6thIN4AaABAg",
    "source": "youtube",
    "title": "My HONEST UNIVERSITY EXPERIENCE at a &quot;TOP&quot; UK UNIVERSITY | York St John and Bristol University",
    "body": "Thank u for sharing your experience at universities in the UK, and thank u again for being honest about universities in the UK. and I wish the best for your life.",
    "upvotes": 1,
    "date": "2023-08-19T23:31:58Z",
    "author": "@Ali99k"
  },
  {
    "id": "Ugy1Qp4DOPqgW_QHknJ4AaABAg",
    "source": "youtube",
    "title": "My HONEST UNIVERSITY EXPERIENCE at a &quot;TOP&quot; UK UNIVERSITY | York St John and Bristol University",
    "body": "I like your video so much especially your speaking. It&#39;s so many helpful and clear that you really motivate me so much. I can&#39;t help but appreciate you. You are one the most wonderful person I have ever seen.",
    "upvotes": 2,
    "date": "2020-08-07T15:35:57Z",
    "author": "@fahimasif9568"
  },
  {
    "id": "Ugwd_mXax-PVYeo0UNB4AaABAg",
    "source": "youtube",
    "title": "My HONEST UNIVERSITY EXPERIENCE at a &quot;TOP&quot; UK UNIVERSITY | York St John and Bristol University",
    "body": "I absolutely learned a lot of your life. like your haunted childhood experience, how you become a YouTuber and your universities stories. Thanks so much for sharing Emma. I really enjoyed to heard all about that. <br>Time passed so fast I watch 30 minutes but I feel like just 10 minutes. Because your life experience is absolutely great. <br>Cheers 🍻",
    "upvotes": 2,
    "date": "2020-08-09T15:22:15Z",
    "author": "@Nal2000"
  },
  {
    "id": "Ugzgk9ntyWCwdqr566d4AaABAg",
    "source": "youtube",
    "title": "My HONEST UNIVERSITY EXPERIENCE at a &quot;TOP&quot; UK UNIVERSITY | York St John and Bristol University",
    "body": "There is a lot of beautiful teacher in the world you are one of them. the way you explain it priceless and your lovely voice awesome.",
    "upvotes": 1,
    "date": "2020-12-31T04:20:56Z",
    "author": "@zillurrahman1759"
  },
  {
    "id": "UgwH5Dznnnv1KfVidk14AaABAg",
    "source": "youtube",
    "title": "My HONEST UNIVERSITY EXPERIENCE at a &quot;TOP&quot; UK UNIVERSITY | York St John and Bristol University",
    "body": "Awww...I love you so much, especially your voice, it&#39;s really beautiful &lt;3 I am practising British accent day-to-day so you know, it&#39;s lucky for me to know you &lt;3",
    "upvotes": 3,
    "date": "2020-07-23T11:51:41Z",
    "author": "@tiendung2048"
  },
  {
    "id": "UgwKQzO5jMTWGJKlOZZ4AaABAg",
    "source": "youtube",
    "title": "My HONEST UNIVERSITY EXPERIENCE at a &quot;TOP&quot; UK UNIVERSITY | York St John and Bristol University",
    "body": "Thank you so much for your wonderful sharing of your yesteryears about your educational journey trials and tribulations .:) As a matter of fact you&#39;ve made a power move to start YouTube channel instead of pursuing PHD if you will. As far as teaching English online goes, you have what it takes to be a good English teacher and l believe that so wholeheartedly.  You surmounted all the impossible and reach this far,  you must be very proud of yourself. The sky is the limit.  All the best Emma!  👍💪💖",
    "upvotes": 2,
    "date": "2021-07-28T06:45:43Z",
    "author": "@stefaniechong9640"
  },
  {
    "id": "UgwEs89-PJLRwePwVqZ4AaABAg",
    "source": "youtube",
    "title": "My HONEST UNIVERSITY EXPERIENCE at a &quot;TOP&quot; UK UNIVERSITY | York St John and Bristol University",
    "body": "You are the best, I like so much the way you talk.<br>I love so much this journey  that it is learning English.",
    "upvotes": 0,
    "date": "2023-06-05T17:01:53Z",
    "author": "@maria_maria88"
  },
  {
    "id": "UgwbTejb3ec4CT-oi694AaABAg",
    "source": "youtube",
    "title": "My HONEST UNIVERSITY EXPERIENCE at a &quot;TOP&quot; UK UNIVERSITY | York St John and Bristol University",
    "body": "Hola Emma Thank U so much for your video, U are a strong woman who pursues her goals despite the difficulties.<br>You are an honest person, it’s not easy to meet someone like u nowadays.<br>I’m sorry for your not good experience in Spain at the beginning..<br>I was sick of vertigo psychogenic for stress I understand your bad experience wit this illness.<br>Thank U for telling us your experiences at the University. <br>U are a successful woman, your number of subscribers are growing  very fast , U are a famous YouTuber now, <br>I want to apologize for my long comment, I promise U this is the last one so long.<br>Hasta Pronto!<br>Muchas Gracias",
    "upvotes": 1,
    "date": "2019-11-23T19:31:14Z",
    "author": "@armandojimenez7838"
  },
  {
    "id": "UgyPc69Cl71dk5FRril4AaABAg",
    "source": "youtube",
    "title": "My HONEST UNIVERSITY EXPERIENCE at a &quot;TOP&quot; UK UNIVERSITY | York St John and Bristol University",
    "body": "I have 5 little grandchildren now living in Tokyo. I found your English Teaching style just weeks ago. I know Kids will learn from a teacher they like. I will refer your Channel to their parents first and subsequently to them. Btw, around from track <a href=\"https://www.youtube.com/watch?v=ZbfO36ZNios&amp;t=1380\">23:00</a> mins you almost got emotionally teary. In the later part I laugh as you revealed you wanted to become a YouTuber. I’m a serious person seldom laugh, except to my family and relatives but today I laughed alone. I think that Youtube needs a lot of people like you. Grateful here.",
    "upvotes": 1,
    "date": "2024-05-02T02:06:13Z",
    "author": "@alfconde7826"
  },
  {
    "id": "Ugy9NgLkfLb38iV0ac14AaABAg",
    "source": "youtube",
    "title": "My HONEST UNIVERSITY EXPERIENCE at a &quot;TOP&quot; UK UNIVERSITY | York St John and Bristol University",
    "body": "I was preparing for my University education in the UK at York St. John&#39;s and I&#39;m really really glad that I watched this video without even missing a second. Thank you very much for the information, it was really very helpful.",
    "upvotes": 14,
    "date": "2021-06-27T21:54:12Z",
    "author": "@adithsuday"
  },
  {
    "id": "UgzSLDbsjhxyQOFaP_14AaABAg",
    "source": "youtube",
    "title": "My HONEST UNIVERSITY EXPERIENCE at a &quot;TOP&quot; UK UNIVERSITY | York St John and Bristol University",
    "body": "Thanks for sharing your experiences at Uni. Sorry to hear about the bad ones, but in the end all of us have to go through that anyway and that extends for life. So, you ended up being a youtuber? Of course not. In reality you became an exceptional teacher, so much better than some you once had. We&#39;ve gained an exceptional source of learning. So cute, so adorable. Keep it up!",
    "upvotes": 0,
    "date": "2019-11-25T20:53:08Z",
    "author": "@ricardoroque9055"
  },
  {
    "id": "UgyZdAG9EhWMqeuMYJt4AaABAg",
    "source": "youtube",
    "title": "My HONEST UNIVERSITY EXPERIENCE at a &quot;TOP&quot; UK UNIVERSITY | York St John and Bristol University",
    "body": "<b>I appreciated so much this report about your academic experiences, and l tell you: thanks and congratulations, and be so luck too, lol !!!</b>",
    "upvotes": 28,
    "date": "2019-11-22T19:23:25Z",
    "author": "@PauloSilva-il8wf"
  },
  {
    "id": "UgyjF76rslV2Fum6OF54AaABAg",
    "source": "youtube",
    "title": "My HONEST UNIVERSITY EXPERIENCE at a &quot;TOP&quot; UK UNIVERSITY | York St John and Bristol University",
    "body": "I found you a while back.And the first day when I was watching your vedios, I fallen in love with your teaching gestures.Really your teaching style is as beautiful as yours.. I am not so good in english but I think your vedios will be very helpful not only for me but aslo others.Keep me in your prayers so that I will be a good english speaker.Afterall ,thank you so much for helping us by sharing your vedios..",
    "upvotes": 1,
    "date": "2020-01-26T19:00:52Z",
    "author": "@NahidHasan-ic3ot"
  },
  {
    "id": "UgxznMjtOpsv4fbQ0rR4AaABAg",
    "source": "youtube",
    "title": "My HONEST UNIVERSITY EXPERIENCE at a &quot;TOP&quot; UK UNIVERSITY | York St John and Bristol University",
    "body": "I love your smile Emma and you smile all the time when you talk. That’s a fun British teach I’ve ever seen 🙂🤣",
    "upvotes": 5,
    "date": "2019-11-22T20:33:43Z",
    "author": "@longnguyen9638"
  },
  {
    "id": "Ugw-hsGJwcu48qN2gYV4AaABAg",
    "source": "youtube",
    "title": "ALL ABOUT OUR HOSTEL | ST JOHNS MEDICAL COLLEGE BANGALORE🏠❤️✨",
    "body": "Please share visuals of the class room, dissecting halls, library if possible and do they teach using DG boards. Please share as many vlogs as u can, love them , thank you ❤❤❤",
    "upvotes": 3,
    "date": "2025-10-15T06:59:48Z",
    "author": "@Sigmaspleen"
  },
  {
    "id": "Ugwpd4pFlX5Uvd5f6uZ4AaABAg",
    "source": "youtube",
    "title": "ALL ABOUT OUR HOSTEL | ST JOHNS MEDICAL COLLEGE BANGALORE🏠❤️✨",
    "body": "Chechi bsc nursing student nte hostel lum eth pole thanne ano.  College le dress and phone nte okke rules and regulations parayaavo",
    "upvotes": 0,
    "date": "2026-03-18T15:10:37Z",
    "author": "@alinannaeldhose2239"
  },
  {
    "id": "UgzTKa6VGIBjFeg0qt94AaABAg",
    "source": "youtube",
    "title": "ALL ABOUT OUR HOSTEL | ST JOHNS MEDICAL COLLEGE BANGALORE🏠❤️✨",
    "body": "Chechi i was denied eligibility in the St johns college when i went for document verification because in the bulletin it was stated 7 yrs of continuous schooling in india.But i only studied from 7-12 in india and 6 th in Oman. So i asked them to provide an exception for this ,but they strictly denied ..now i cant apply for Rc8 category 😢",
    "upvotes": 3,
    "date": "2025-07-14T19:10:54Z",
    "author": "@karaokedude3174"
  },
  {
    "id": "UgzIWgrt3I3LG9q15ot4AaABAg",
    "source": "youtube",
    "title": "ALL ABOUT OUR HOSTEL | ST JOHNS MEDICAL COLLEGE BANGALORE🏠❤️✨",
    "body": "Hi  I show you r videos in few days on instagram iam wrote neet exam and i have score 193 is it any chance for admission in your medical college",
    "upvotes": 0,
    "date": "2025-07-15T01:36:04Z",
    "author": "@RajalakshmiK-j3b"
  },
  {
    "id": "UgxqzNs8oUGcZ8JW_cJ4AaABAg",
    "source": "youtube",
    "title": "MY CAMBRIDGE COLLEGE | ST. JOHN&#39;S COLLEGE TOUR",
    "body": "Thank you for making this video. I&#39;m a brazilian student and I can&#39;t even imagine myself in a place so full of history and tradition as Cambridge! You&#39;re amazing!!",
    "upvotes": 33,
    "date": "2019-04-21T11:39:02Z",
    "author": "@tamiresbenedita8216"
  },
  {
    "id": "UgwjfRddSGUmtA3uM354AaABAg",
    "source": "youtube",
    "title": "MY CAMBRIDGE COLLEGE | ST. JOHN&#39;S COLLEGE TOUR",
    "body": "Thanks for the video tour, Elena. It was quite enjoyable, reminding me of an impromptu visit with one of my college professors, when he gave me a tour of the faculty areas and living quarters at St. John&#39;s. I wish you much success beyond the college years. <br><br><br><br>RIP Mr. George Watson, Fellow English Dept, St. John&#39;s, Cambridge,  for introducing me at the University of Georgia in the 1980&#39;s to one of my great loves, the modern British novel. A time when students of all ethnicities and political persuasions could and would voluntarily breathe the same air on college campuses.",
    "upvotes": 10,
    "date": "2019-11-23T18:15:18Z",
    "author": "@itzcyclops306"
  },
  {
    "id": "UgyIVHWt2rFolgmj2m14AaABAg",
    "source": "youtube",
    "title": "MY CAMBRIDGE COLLEGE | ST. JOHN&#39;S COLLEGE TOUR",
    "body": "Enjoyed your video guide Elena - how the college has changed and expanded since my time (Natural Sciences 1960-63) with so much more by way of student facilities.  Also, there were no women students in my day and St John&#39;s looks altogether a more friendly supportive environment too. Amazingly my old room (K3 2nd Court) is now the JCR/Buttery! All the best for your studies.  Anthony",
    "upvotes": 54,
    "date": "2020-04-13T18:59:52Z",
    "author": "@antohosm43"
  },
  {
    "id": "Ugyd5oieLn-W2g9gTa94AaABAg",
    "source": "youtube",
    "title": "MY CAMBRIDGE COLLEGE | ST. JOHN&#39;S COLLEGE TOUR",
    "body": "Thanks very much for this. I was an undergraduate here nearly half a century ago, and it&#39;s great to see that, apart from the new library, things have hardly changed.",
    "upvotes": 8,
    "date": "2020-09-02T12:34:53Z",
    "author": "@robertbilling6266"
  },
  {
    "id": "UgwLWNvWF6N8iUaQGvV4AaABAg",
    "source": "youtube",
    "title": "MY CAMBRIDGE COLLEGE | ST. JOHN&#39;S COLLEGE TOUR",
    "body": "I went to St John&#39;s May Ball and had attended numerous formals, thanks to my friend who&#39;s a member there.  St John&#39;s is gorgeous beyond belief.  You&#39;re lucky to have matriculated there.",
    "upvotes": 0,
    "date": "2023-09-05T12:03:39Z",
    "author": "@jarrodsio"
  },
  {
    "id": "UgzFj-VremxMjdVUCbx4AaABAg",
    "source": "youtube",
    "title": "MY CAMBRIDGE COLLEGE | ST. JOHN&#39;S COLLEGE TOUR",
    "body": "Thank you so much for this! I’ve been looking into Cambridge and am trying to get a better look at this particular school!",
    "upvotes": 7,
    "date": "2019-08-06T20:04:21Z",
    "author": "@meganhall1832"
  },
  {
    "id": "UgwKqyJu0Uf3Uw95q1J4AaABAg",
    "source": "youtube",
    "title": "MY CAMBRIDGE COLLEGE | ST. JOHN&#39;S COLLEGE TOUR",
    "body": "lol when she came out after showing us the hall with all the people in there gowns there were these kids just looking like what the hell is going on",
    "upvotes": 1,
    "date": "2020-11-30T15:57:53Z",
    "author": "@muireannodonovan9038"
  },
  {
    "id": "Ugxyil6YHvHNufTGvUZ4AaABAg",
    "source": "youtube",
    "title": "MY CAMBRIDGE COLLEGE | ST. JOHN&#39;S COLLEGE TOUR",
    "body": "No se porque me recordó al castillo de Howards en Harry Potter, me pareció muy familiar el patio y la biblioteca... Es un hermoso lugar, me hubiera gustado estudiar en ese colegio, tiene mucho de lo que me gusta, tanto en infraestructura como en pedagogía...",
    "upvotes": 0,
    "date": "2021-11-18T17:38:01Z",
    "author": "@cuentodelasanimas8113"
  },
  {
    "id": "UgyifbT_Kcxed95gtTp4AaABAg",
    "source": "youtube",
    "title": "The BEST Parts About St. John&#39;s University - Campus Interviews - LTU",
    "body": "Check out some of the other videos on this channel for more interesting conversations! <br>What are your thoughts on these students views? Do you want to be a student at St. John&#39;s University?",
    "upvotes": 4,
    "date": "2019-04-11T03:51:26Z",
    "author": "@LetsTalkUniversity"
  },
  {
    "id": "UgxFZAckku8ejnVkPSh4AaABAg",
    "source": "youtube",
    "title": "The BEST Parts About St. John&#39;s University - Campus Interviews - LTU",
    "body": "According to the stats it&#39;s mostly white and equal parts asian, Black and Latino yet there&#39;s 1 asian, and 1 Latino? Like why?",
    "upvotes": 3,
    "date": "2019-06-07T04:54:44Z",
    "author": "@jessiemayfield6749"
  },
  {
    "id": "UgzLi3oXfedKkJz0BFt4AaABAg",
    "source": "youtube",
    "title": "The BEST Parts About St. John&#39;s University - Campus Interviews - LTU",
    "body": "Good video. I&#39;m looking to come to St. John&#39;s from Belgium for my semester abroad to study tourism. The other option for me in the US is in South Dakota, which is nice in its own way, but Queens appeals to me a bit more. How is the connection to Manhattan?",
    "upvotes": 3,
    "date": "2022-02-17T21:15:24Z",
    "author": "@smoshbooz"
  },
  {
    "id": "UgzoUhm6_ljqVn5l3iZ4AaABAg",
    "source": "youtube",
    "title": "Durham Colleges - The complete guide/tour",
    "body": "I’m 27 and work for Royal Mail Durham depot and I deliver to pretty much all of these colleges quite regularly and I love to see the people who go to the colleges they always look like they’re having a great time",
    "upvotes": 3,
    "date": "2026-02-10T02:28:07Z",
    "author": "@arronwatson1"
  },
  {
    "id": "Ugw0-cypNozTISr1e1J4AaABAg",
    "source": "youtube",
    "title": "Durham Colleges - The complete guide/tour",
    "body": "If anyone is interested, here&#39;s a few things about the colleges I&#39;ve learnt from my first year in Durham: <br>1. The vast majority of people fall in love with their college, even if it&#39;s not the one they originally picked. I was reallocated but now I honestly can&#39;t imagine being at a different college<br>2. Durham is a small city and most sites are within easy walking distance of all colleges<br>3. Most colleges allow guests to participate in their formals and events, so you may be able to experience a gowned formal at a friend&#39;s college, or vice versa <br>4. You will be able to make friends with people from other colleges. Most people will be lovely, but don&#39;t feel like you can only get to know the people on your corridor <br>5. You tend to get out of the colleges what you put in. If you spend a lot of time in the college bar or with college mates, you&#39;ll feel part of the community very quickly. On the other hand, some choose to spend more time with course or society mates, and they&#39;re equally happy <br><br>Hope that&#39;s helpful!",
    "upvotes": 341,
    "date": "2020-09-01T13:29:39Z",
    "author": "@annabelhay7928"
  },
  {
    "id": "UgyW9eRq9hpUtd1oqm54AaABAg",
    "source": "youtube",
    "title": "Durham Colleges - The complete guide/tour",
    "body": "On a Durham YT binge right now, I’m coming in September for English Lit! Honestly can’t wait, love the video :-)",
    "upvotes": 51,
    "date": "2020-08-30T12:12:29Z",
    "author": "@lizzieirwin588"
  },
  {
    "id": "UgxnyDYjx6FZJxiGFs14AaABAg",
    "source": "youtube",
    "title": "Durham Colleges - The complete guide/tour",
    "body": "I’m not a uni student but I’ve hopped the fence at collingwood astro more than 100 times it’s pretty class",
    "upvotes": 11,
    "date": "2021-08-16T08:50:11Z",
    "author": "@134splashymothfan7"
  },
  {
    "id": "UgzMN8fZ6pKMz7_Nokl4AaABAg",
    "source": "youtube",
    "title": "Durham Colleges - The complete guide/tour",
    "body": "I am a mother from Hong Kong. This video is very useful for me and my daughter to choose college preference.Thank you very much",
    "upvotes": 18,
    "date": "2022-03-18T05:16:01Z",
    "author": "@aprilyau123"
  },
  {
    "id": "UgxKpz5vC3AKGPmbzvB4AaABAg",
    "source": "youtube",
    "title": "Durham Colleges - The complete guide/tour",
    "body": "I&#39;m so glad there is finally a good college guide video! THANK YOU - when I was choosing my college, this is exactly what I would have needed! You&#39;ll be helping A LOT of people with this video :)",
    "upvotes": 119,
    "date": "2020-08-30T00:09:05Z",
    "author": "@mayamccann986"
  },
  {
    "id": "UgwobuCNffSdm0KU4sd4AaABAg",
    "source": "youtube",
    "title": "Durham Colleges - The complete guide/tour",
    "body": "Thanks for the complete overview &amp; tour of all the colleges, Charlie. It was really nice to be able to see Durham and the surrounding/colleges in the video. It brings back good old memories when i was there for my postgraduate studies in 2011-2012. By the way, I am a member of Hatfield College and can certainly say that I am definitely not stuck up. 😁😊",
    "upvotes": 0,
    "date": "2025-02-24T09:54:17Z",
    "author": "@Nazlin_Nasir"
  },
  {
    "id": "UgxIaJHwwrB0g-7-ZyF4AaABAg",
    "source": "youtube",
    "title": "Durham Colleges - The complete guide/tour",
    "body": "Thank you for this video! I was unsure on what college to pick but this has made it easier for me. I got an offer for Theology and Religion back in January.",
    "upvotes": 0,
    "date": "2024-04-05T13:19:21Z",
    "author": "@LilKevv"
  },
  {
    "id": "Ugz_jppo1hlgmKo00Pt4AaABAg",
    "source": "youtube",
    "title": "Durham Colleges - The complete guide/tour",
    "body": "Your videos are sooo helpful, got into Durham this year and this is like a complete guide before entering the uni. Thankyou :) <br>Hope to see you there",
    "upvotes": 3,
    "date": "2021-08-19T18:29:23Z",
    "author": "@Itsybitsyak"
  },
  {
    "id": "UgxFX5l5sLJirSJF2ld4AaABAg",
    "source": "youtube",
    "title": "Durham Colleges - The complete guide/tour",
    "body": "I have been searching for a video like this for MONTHS thank you so so much you&#39;ve just saved hours of my life 🤩",
    "upvotes": 15,
    "date": "2020-09-11T06:08:33Z",
    "author": "@hannah-qg5fl"
  },
  {
    "id": "UgyDP8v6Yn8NuKT_hdh4AaABAg",
    "source": "youtube",
    "title": "Durham Colleges - The complete guide/tour",
    "body": "Just watched this out of curiosity because it came up in my recommended and it makes Durham look a lot better and nicer than it is ahah",
    "upvotes": 1,
    "date": "2021-02-15T23:03:12Z",
    "author": "@danielscott8998"
  },
  {
    "id": "Ugz9_gt_-sjJVLQZgLB4AaABAg",
    "source": "youtube",
    "title": "Durham Colleges - The complete guide/tour",
    "body": "I am DREAMING of Durham rn, and I&#39;m really hoping to get into Trevs, wish me luck bc im feeling like im not gonna get in!",
    "upvotes": 2,
    "date": "2024-06-18T21:20:48Z",
    "author": "@rosalindsian"
  },
  {
    "id": "UgypFiS4jObs8i87cwh4AaABAg",
    "source": "youtube",
    "title": "Durham Colleges - The complete guide/tour",
    "body": "my school has close relations with van mildert college, it’s a great laugh and has a great community vibe with everyone being like one family, just watch out for the swans",
    "upvotes": 9,
    "date": "2020-08-29T15:25:22Z",
    "author": "@neavewallace8173"
  },
  {
    "id": "UgxRIE2F9j9qSy2HJqx4AaABAg",
    "source": "youtube",
    "title": "Durham Colleges - The complete guide/tour",
    "body": "i am hoping to apply to go this year and just looking at these colleges and reading about them im 100% aiming for collingwood or aidans they are the colleges i feel i would be most at home in and i really love the thought of catered so its one less stress i have ontop of the studies i want to do it will give me more of a chance to do societies and sports clubs and study",
    "upvotes": 7,
    "date": "2022-04-09T22:10:41Z",
    "author": "@stars_wraith_xL"
  },
  {
    "id": "UgzYRM-AONyDnLJUlRZ4AaABAg",
    "source": "youtube",
    "title": "Jain University, Jayanagar - Campus Tour &amp; Honest Student Experience | Kavach Khanna",
    "body": "Thanks for making the overview video of the Jain Jayanagar campus Kavach Bhaiya, it indeed looked helpful to me ✌🏻",
    "upvotes": 15,
    "date": "2022-07-15T07:18:00Z",
    "author": "@ankitsaharia878"
  },
  {
    "id": "UgzO1AMNhimWw_bFPyp4AaABAg",
    "source": "youtube",
    "title": "Jain University, Jayanagar - Campus Tour &amp; Honest Student Experience | Kavach Khanna",
    "body": "It would be dope if you could make a video about accommodations around the Jai Nagar and CMS campus of Jain University",
    "upvotes": 11,
    "date": "2022-07-16T14:11:07Z",
    "author": "@user-fi7up4bw6u"
  },
  {
    "id": "Ugx-Fcf12otzKRKS6Md4AaABAg",
    "source": "youtube",
    "title": "Jain University, Jayanagar - Campus Tour &amp; Honest Student Experience | Kavach Khanna",
    "body": "Please  do cms jain college  tour, it&#39;s for management like bba and ba ,it would  helpful if u do it",
    "upvotes": 31,
    "date": "2022-07-15T07:12:53Z",
    "author": "@infinity9287"
  },
  {
    "id": "UgxzhC4ns8IjSIoQwiJ4AaABAg",
    "source": "youtube",
    "title": "Jain University, Jayanagar - Campus Tour &amp; Honest Student Experience | Kavach Khanna",
    "body": "I watched your video on the engineering campus but you missed a few details about student&#39;s reviews and the atmosphere on the campus. Please make video on the computer science department and ask students about the quality of education they are getting at the campus and also take reviews from teachers. Show us the computer labs, classrooms etc. Please make detailed video on this topic because it will be very helpul for freshers of computer science department.",
    "upvotes": 16,
    "date": "2022-07-15T10:27:34Z",
    "author": "@varungandhi2576"
  },
  {
    "id": "Ugw9AKQwBvw-27yEdoF4AaABAg",
    "source": "youtube",
    "title": "Jain University, Jayanagar - Campus Tour &amp; Honest Student Experience | Kavach Khanna",
    "body": "Kavach bhaiya please make some videos on accommodations near Jain University whether a pg or a rented flat/rk…. I’m in very much need of it, please bhaiya.!!!!🙏🏼❤️",
    "upvotes": 7,
    "date": "2022-07-17T09:55:23Z",
    "author": "@abhinavgovind9626"
  },
  {
    "id": "Ugx-Zo7W2nvLJOAp8kp4AaABAg",
    "source": "youtube",
    "title": "Jain University, Jayanagar - Campus Tour &amp; Honest Student Experience | Kavach Khanna",
    "body": "hey kavach have been watching all your videos since a few months. please make a campus tour of jain CMS , lalbagh road!",
    "upvotes": 5,
    "date": "2022-07-15T07:42:35Z",
    "author": "@vaibhavakumarjv8442"
  },
  {
    "id": "UgzcPjA1qgWFKJ59o_p4AaABAg",
    "source": "youtube",
    "title": "Jain University, Jayanagar - Campus Tour &amp; Honest Student Experience | Kavach Khanna",
    "body": "I was looking for SLS wat prep got your video of last year the content was really good, can you make similar video for this year as well",
    "upvotes": 1,
    "date": "2022-07-15T14:57:49Z",
    "author": "@aasthaashish7007"
  },
  {
    "id": "Ugy7-For5_-E32AuwdB4AaABAg",
    "source": "youtube",
    "title": "Jain University, Jayanagar - Campus Tour &amp; Honest Student Experience | Kavach Khanna",
    "body": "The location of Jain Jayanagar campus is great! It&#39;s centrality in Bangalore and it is surrounded by some malls, great restaurants and cafeterias. The only drawback is there&#39;s no sports facility due to space constraint.<br><br>I am a Jainite btw",
    "upvotes": 27,
    "date": "2022-07-15T13:50:12Z",
    "author": "@preetaexoxo376"
  },
  {
    "id": "UgzwfcQ-Lc1XkDiwYWd4AaABAg",
    "source": "youtube",
    "title": "YORK ST JOHN UNIVERSITY (YORK CAMPUS) !",
    "body": "Good afternoon, i enjoyed ur video but plz how much is the deposit fee and how is the payment plan plz , help a sister",
    "upvotes": 0,
    "date": "2024-02-13T15:47:12Z",
    "author": "@umahmercy9540"
  },
  {
    "id": "Ugy_QXP6pa-ts199SKF4AaABAg",
    "source": "youtube",
    "title": "YORK ST JOHN UNIVERSITY (YORK CAMPUS) !",
    "body": "Hi ella i am coming in this week . And i paid half tuition fees and the rest of fees can pay after 5 month ?",
    "upvotes": 1,
    "date": "2025-01-26T08:33:56Z",
    "author": "@fearlessbeast5456"
  },
  {
    "id": "UgyswZU51Xg24ITLBeJ4AaABAg",
    "source": "youtube",
    "title": "YORK ST JOHN UNIVERSITY (YORK CAMPUS) !",
    "body": "I have an offer with YSJ York campus, but I was linked with a Nigerian agent but I want to be sure I am in the right place. Kindly educate me",
    "upvotes": 0,
    "date": "2023-04-30T14:16:54Z",
    "author": "@ayo_rinde"
  },
  {
    "id": "Ugxp0sHLMFBdzBYFvvh4AaABAg",
    "source": "youtube",
    "title": "YORK ST JOHN UNIVERSITY (YORK CAMPUS) !",
    "body": "How many months of summer holidays student get with 1 year master&#39;s degree in the york st john university?<br>I am asking because I can do a full time job during the summer break",
    "upvotes": 1,
    "date": "2024-08-12T18:39:50Z",
    "author": "@haidarshaikh7369"
  },
  {
    "id": "Ugw1mGfWgASNz2jp6Vd4AaABAg",
    "source": "youtube",
    "title": "YORK ST JOHN UNIVERSITY (YORK CAMPUS) !",
    "body": "Hello Ella!...<br>Is there any university programs that held in London Campus..<br>How was the welcome week celebration??<br>I got admission from York St John university london campus",
    "upvotes": 2,
    "date": "2023-08-03T10:31:23Z",
    "author": "@itsme.anakha"
  },
  {
    "id": "UgxPNBAINliaPhuEVLJ4AaABAg",
    "source": "youtube",
    "title": "YORK ST JOHN UNIVERSITY (YORK CAMPUS) !",
    "body": "I&#39;m an international student from Ghana will be coming over this year and I will be glad if you can please help me around, can I kindly text you",
    "upvotes": 1,
    "date": "2023-03-07T22:01:31Z",
    "author": "@PETERTECHTIPS"
  },
  {
    "id": "UgyxwgF0mXQurt8Om3J4AaABAg",
    "source": "youtube",
    "title": "YORK ST JOHN UNIVERSITY (YORK CAMPUS) !",
    "body": "Hello Ella, great video you have here.<br>I tried reaching out on your Instagram but your dm is locked, your response will be appreciated.",
    "upvotes": 1,
    "date": "2024-08-18T12:50:20Z",
    "author": "@loveaubrey4198"
  }
]